package com.telesoftas.services;

import com.crashlytics.android.Crashlytics;
import com.fridaylab.util.TimeSpan;
import java.io.BufferedReader;
import java.io.InputStream;

class FileService$ConnectedThread
  extends Thread
{
  private final String b;
  private InputStream c = null;
  private BufferedReader d = null;
  
  public FileService$ConnectedThread(FileService paramFileService, String paramString)
  {
    this.b = paramString;
    FileService.a(paramFileService, true);
  }
  
  private void a(long paramLong)
  {
    long l = System.nanoTime();
    if (paramLong > l) {
      Thread.sleep(TimeSpan.a(paramLong - l));
    }
  }
  
  public void a()
  {
    FileService.a(this.a, false);
    try
    {
      this.d.close();
    }
    catch (Exception localException1)
    {
      for (;;)
      {
        try
        {
          this.c.close();
          return;
        }
        catch (Exception localException2)
        {
          Crashlytics.a(localException2);
        }
        localException1 = localException1;
        Crashlytics.a(localException1);
      }
    }
  }
  
  /* Error */
  public void run()
  {
    // Byte code:
    //   0: aload_0
    //   1: getfield 16	com/telesoftas/services/FileService$ConnectedThread:a	Lcom/telesoftas/services/FileService;
    //   4: invokestatic 68	com/telesoftas/services/FileService:a	(Lcom/telesoftas/services/FileService;)Landroid/content/Context;
    //   7: ldc 70
    //   9: iconst_0
    //   10: invokevirtual 76	android/content/Context:getSharedPreferences	(Ljava/lang/String;I)Landroid/content/SharedPreferences;
    //   13: getstatic 79	com/telesoftas/utilities/deeper/SettingsUtils:b	Ljava/lang/String;
    //   16: iconst_1
    //   17: invokeinterface 85 3 0
    //   22: istore_1
    //   23: aload_0
    //   24: getfield 16	com/telesoftas/services/FileService$ConnectedThread:a	Lcom/telesoftas/services/FileService;
    //   27: astore_2
    //   28: iload_1
    //   29: iconst_1
    //   30: if_icmpne +87 -> 117
    //   33: iconst_1
    //   34: istore_3
    //   35: aload_2
    //   36: iload_3
    //   37: invokestatic 87	com/telesoftas/services/FileService:b	(Lcom/telesoftas/services/FileService;Z)Z
    //   40: pop
    //   41: new 89	com/fridaylab/deeper/communication/ParseResult
    //   44: dup
    //   45: invokespecial 90	com/fridaylab/deeper/communication/ParseResult:<init>	()V
    //   48: astore 5
    //   50: invokestatic 95	com/telesoftas/hardware/HardwareJni:resetPacketParser	()V
    //   53: ldc 96
    //   55: aload_0
    //   56: getfield 16	com/telesoftas/services/FileService$ConnectedThread:a	Lcom/telesoftas/services/FileService;
    //   59: invokestatic 99	com/telesoftas/services/FileService:b	(Lcom/telesoftas/services/FileService;)F
    //   62: fdiv
    //   63: invokestatic 105	java/lang/Math:round	(F)I
    //   66: i2l
    //   67: lstore 6
    //   69: aload_0
    //   70: getfield 25	com/telesoftas/services/FileService$ConnectedThread:b	Ljava/lang/String;
    //   73: ldc 107
    //   75: invokevirtual 113	java/lang/String:endsWith	(Ljava/lang/String;)Z
    //   78: istore 8
    //   80: iconst_0
    //   81: istore 9
    //   83: iconst_3
    //   84: newarray int
    //   86: astore 10
    //   88: iconst_0
    //   89: istore 11
    //   91: aload_0
    //   92: aload_0
    //   93: getfield 16	com/telesoftas/services/FileService$ConnectedThread:a	Lcom/telesoftas/services/FileService;
    //   96: invokestatic 68	com/telesoftas/services/FileService:a	(Lcom/telesoftas/services/FileService;)Landroid/content/Context;
    //   99: aload_0
    //   100: getfield 25	com/telesoftas/services/FileService$ConnectedThread:b	Ljava/lang/String;
    //   103: invokestatic 118	com/telesoftas/utilities/FileUtils:a	(Landroid/content/Context;Ljava/lang/String;)Ljava/io/InputStream;
    //   106: putfield 21	com/telesoftas/services/FileService$ConnectedThread:c	Ljava/io/InputStream;
    //   109: aload_0
    //   110: getfield 21	com/telesoftas/services/FileService$ConnectedThread:c	Ljava/io/InputStream;
    //   113: ifnonnull +19 -> 132
    //   116: return
    //   117: iconst_0
    //   118: istore_3
    //   119: goto -84 -> 35
    //   122: astore 12
    //   124: aload 12
    //   126: invokestatic 60	com/crashlytics/android/Crashlytics:a	(Ljava/lang/Throwable;)V
    //   129: goto -20 -> 109
    //   132: aload_0
    //   133: new 49	java/io/BufferedReader
    //   136: dup
    //   137: new 120	java/io/InputStreamReader
    //   140: dup
    //   141: aload_0
    //   142: getfield 21	com/telesoftas/services/FileService$ConnectedThread:c	Ljava/io/InputStream;
    //   145: invokespecial 123	java/io/InputStreamReader:<init>	(Ljava/io/InputStream;)V
    //   148: invokespecial 126	java/io/BufferedReader:<init>	(Ljava/io/Reader;)V
    //   151: putfield 23	com/telesoftas/services/FileService$ConnectedThread:d	Ljava/io/BufferedReader;
    //   154: sipush 4600
    //   157: newarray char
    //   159: astore 13
    //   161: iconst_0
    //   162: istore 14
    //   164: iconst_m1
    //   165: istore 15
    //   167: iconst_m1
    //   168: istore 16
    //   170: aload_0
    //   171: getfield 16	com/telesoftas/services/FileService$ConnectedThread:a	Lcom/telesoftas/services/FileService;
    //   174: invokestatic 129	com/telesoftas/services/FileService:c	(Lcom/telesoftas/services/FileService;)Z
    //   177: ifeq +581 -> 758
    //   180: lload 6
    //   182: invokestatic 37	java/lang/System:nanoTime	()J
    //   185: ladd
    //   186: lstore 25
    //   188: iload 16
    //   190: ifle +674 -> 864
    //   193: aload 13
    //   195: iload 16
    //   197: aload 13
    //   199: iconst_0
    //   200: iload 14
    //   202: iload 16
    //   204: isub
    //   205: invokestatic 133	java/lang/System:arraycopy	(Ljava/lang/Object;ILjava/lang/Object;II)V
    //   208: iload 14
    //   210: iload 16
    //   212: isub
    //   213: istore 14
    //   215: iconst_m1
    //   216: istore 16
    //   218: iconst_m1
    //   219: istore 15
    //   221: goto +643 -> 864
    //   224: iload 29
    //   226: iload 27
    //   228: if_icmpge +681 -> 909
    //   231: aload 13
    //   233: iload 29
    //   235: caload
    //   236: istore 30
    //   238: iload 30
    //   240: bipush 10
    //   242: if_icmpeq +641 -> 883
    //   245: iload 30
    //   247: bipush 13
    //   249: if_icmpne +655 -> 904
    //   252: goto +631 -> 883
    //   255: aload_0
    //   256: getfield 23	com/telesoftas/services/FileService$ConnectedThread:d	Ljava/io/BufferedReader;
    //   259: aload 13
    //   261: iload 27
    //   263: sipush 4600
    //   266: iload 27
    //   268: isub
    //   269: invokevirtual 137	java/io/BufferedReader:read	([CII)I
    //   272: istore 31
    //   274: iload 31
    //   276: iconst_m1
    //   277: if_icmpne +691 -> 968
    //   280: iload 27
    //   282: istore 32
    //   284: iload 27
    //   286: istore 28
    //   288: iload 27
    //   290: istore 33
    //   292: iload 28
    //   294: ifne +540 -> 834
    //   297: iconst_m1
    //   298: istore 16
    //   300: iconst_m1
    //   301: istore 34
    //   303: aload_0
    //   304: getfield 23	com/telesoftas/services/FileService$ConnectedThread:d	Ljava/io/BufferedReader;
    //   307: invokevirtual 52	java/io/BufferedReader:close	()V
    //   310: aload_0
    //   311: getfield 21	com/telesoftas/services/FileService$ConnectedThread:c	Ljava/io/InputStream;
    //   314: invokevirtual 55	java/io/InputStream:close	()V
    //   317: invokestatic 95	com/telesoftas/hardware/HardwareJni:resetPacketParser	()V
    //   320: aload_0
    //   321: aload_0
    //   322: getfield 16	com/telesoftas/services/FileService$ConnectedThread:a	Lcom/telesoftas/services/FileService;
    //   325: invokestatic 68	com/telesoftas/services/FileService:a	(Lcom/telesoftas/services/FileService;)Landroid/content/Context;
    //   328: aload_0
    //   329: getfield 25	com/telesoftas/services/FileService$ConnectedThread:b	Ljava/lang/String;
    //   332: invokestatic 118	com/telesoftas/utilities/FileUtils:a	(Landroid/content/Context;Ljava/lang/String;)Ljava/io/InputStream;
    //   335: putfield 21	com/telesoftas/services/FileService$ConnectedThread:c	Ljava/io/InputStream;
    //   338: aload_0
    //   339: new 49	java/io/BufferedReader
    //   342: dup
    //   343: new 120	java/io/InputStreamReader
    //   346: dup
    //   347: aload_0
    //   348: getfield 21	com/telesoftas/services/FileService$ConnectedThread:c	Ljava/io/InputStream;
    //   351: invokespecial 123	java/io/InputStreamReader:<init>	(Ljava/io/InputStream;)V
    //   354: invokespecial 126	java/io/BufferedReader:<init>	(Ljava/io/Reader;)V
    //   357: putfield 23	com/telesoftas/services/FileService$ConnectedThread:d	Ljava/io/BufferedReader;
    //   360: iconst_1
    //   361: istore 36
    //   363: iconst_0
    //   364: istore 35
    //   366: goto +579 -> 945
    //   369: astore 38
    //   371: aload 38
    //   373: invokestatic 60	com/crashlytics/android/Crashlytics:a	(Ljava/lang/Throwable;)V
    //   376: goto -66 -> 310
    //   379: astore 20
    //   381: aload 20
    //   383: invokestatic 60	com/crashlytics/android/Crashlytics:a	(Ljava/lang/Throwable;)V
    //   386: aload_0
    //   387: getfield 23	com/telesoftas/services/FileService$ConnectedThread:d	Ljava/io/BufferedReader;
    //   390: invokevirtual 52	java/io/BufferedReader:close	()V
    //   393: aload_0
    //   394: getfield 21	com/telesoftas/services/FileService$ConnectedThread:c	Ljava/io/InputStream;
    //   397: invokevirtual 55	java/io/InputStream:close	()V
    //   400: return
    //   401: astore 22
    //   403: aload 22
    //   405: invokestatic 60	com/crashlytics/android/Crashlytics:a	(Ljava/lang/Throwable;)V
    //   408: return
    //   409: astore 39
    //   411: aload 39
    //   413: invokestatic 60	com/crashlytics/android/Crashlytics:a	(Ljava/lang/Throwable;)V
    //   416: goto -99 -> 317
    //   419: astore 17
    //   421: aload_0
    //   422: getfield 23	com/telesoftas/services/FileService$ConnectedThread:d	Ljava/io/BufferedReader;
    //   425: invokevirtual 52	java/io/BufferedReader:close	()V
    //   428: aload_0
    //   429: getfield 21	com/telesoftas/services/FileService$ConnectedThread:c	Ljava/io/InputStream;
    //   432: invokevirtual 55	java/io/InputStream:close	()V
    //   435: aload 17
    //   437: athrow
    //   438: iload 8
    //   440: ifeq +311 -> 751
    //   443: aload 13
    //   445: iload 41
    //   447: iconst_2
    //   448: invokestatic 142	com/telesoftas/utilities/ByteUtils:a	([CII)[B
    //   451: astore 45
    //   453: aload 45
    //   455: ifnonnull +18 -> 473
    //   458: iload 27
    //   460: istore 14
    //   462: iload 41
    //   464: istore 15
    //   466: iload 40
    //   468: istore 16
    //   470: goto -300 -> 170
    //   473: iconst_2
    //   474: iload 9
    //   476: if_icmpeq +506 -> 982
    //   479: iconst_2
    //   480: istore 46
    //   482: aload_0
    //   483: getfield 16	com/telesoftas/services/FileService$ConnectedThread:a	Lcom/telesoftas/services/FileService;
    //   486: invokestatic 144	com/telesoftas/services/FileService:d	(Lcom/telesoftas/services/FileService;)Z
    //   489: ifeq +127 -> 616
    //   492: aload_0
    //   493: getfield 16	com/telesoftas/services/FileService$ConnectedThread:a	Lcom/telesoftas/services/FileService;
    //   496: invokestatic 147	com/telesoftas/services/FileService:e	(Lcom/telesoftas/services/FileService;)Z
    //   499: ifeq +117 -> 616
    //   502: iload 46
    //   504: aload 45
    //   506: aload 10
    //   508: aload 5
    //   510: invokestatic 150	com/telesoftas/hardware/HardwareJni:a	(B[B[ILcom/fridaylab/deeper/communication/ParseResult;)F
    //   513: fstore 51
    //   515: fload 51
    //   517: fconst_0
    //   518: fcmpg
    //   519: ifge +21 -> 540
    //   522: iload 27
    //   524: istore 14
    //   526: iload 41
    //   528: istore 15
    //   530: iconst_2
    //   531: istore 9
    //   533: iload 40
    //   535: istore 16
    //   537: goto -367 -> 170
    //   540: new 152	com/telesoftas/hardware/DeeperFishDataPacket
    //   543: dup
    //   544: fload 51
    //   546: aload 5
    //   548: invokevirtual 156	com/fridaylab/deeper/communication/ParseResult:getFishData	()[Lcom/telesoftas/hardware/FishData;
    //   551: invokespecial 159	com/telesoftas/hardware/DeeperFishDataPacket:<init>	(F[Lcom/telesoftas/hardware/FishData;)V
    //   554: astore 52
    //   556: aload 52
    //   558: aload_0
    //   559: getfield 16	com/telesoftas/services/FileService$ConnectedThread:a	Lcom/telesoftas/services/FileService;
    //   562: invokestatic 163	com/telesoftas/services/FileService:f	(Lcom/telesoftas/services/FileService;)I
    //   565: invokevirtual 168	com/telesoftas/hardware/ImagingSignal:a	(I)V
    //   568: aload_0
    //   569: getfield 16	com/telesoftas/services/FileService$ConnectedThread:a	Lcom/telesoftas/services/FileService;
    //   572: invokestatic 129	com/telesoftas/services/FileService:c	(Lcom/telesoftas/services/FileService;)Z
    //   575: ifeq +17 -> 592
    //   578: aload_0
    //   579: getfield 16	com/telesoftas/services/FileService$ConnectedThread:a	Lcom/telesoftas/services/FileService;
    //   582: getfield 171	com/telesoftas/services/FileService:a	Lcom/fridaylab/deeper/communication/DeeperChannel$SignalObserver;
    //   585: aload 52
    //   587: invokeinterface 176 2 0
    //   592: aload_0
    //   593: lload 25
    //   595: invokespecial 178	com/telesoftas/services/FileService$ConnectedThread:a	(J)V
    //   598: iload 27
    //   600: istore 14
    //   602: iload 41
    //   604: istore 15
    //   606: iconst_2
    //   607: istore 9
    //   609: iload 40
    //   611: istore 16
    //   613: goto -443 -> 170
    //   616: iconst_3
    //   617: newarray int
    //   619: astore 48
    //   621: iload 46
    //   623: aload 45
    //   625: aload 48
    //   627: aload 5
    //   629: invokestatic 150	com/telesoftas/hardware/HardwareJni:a	(B[B[ILcom/fridaylab/deeper/communication/ParseResult;)F
    //   632: fstore 49
    //   634: fload 49
    //   636: fconst_0
    //   637: fcmpg
    //   638: ifgt +21 -> 659
    //   641: iload 27
    //   643: istore 14
    //   645: iload 41
    //   647: istore 15
    //   649: iconst_2
    //   650: istore 9
    //   652: iload 40
    //   654: istore 16
    //   656: goto -486 -> 170
    //   659: new 180	com/telesoftas/hardware/DeeperRawDataPacket
    //   662: dup
    //   663: fload 49
    //   665: aload 5
    //   667: invokevirtual 156	com/fridaylab/deeper/communication/ParseResult:getFishData	()[Lcom/telesoftas/hardware/FishData;
    //   670: aload 45
    //   672: aload 48
    //   674: invokespecial 183	com/telesoftas/hardware/DeeperRawDataPacket:<init>	(F[Lcom/telesoftas/hardware/FishData;[B[I)V
    //   677: astore 50
    //   679: aload 50
    //   681: aload_0
    //   682: getfield 16	com/telesoftas/services/FileService$ConnectedThread:a	Lcom/telesoftas/services/FileService;
    //   685: invokestatic 163	com/telesoftas/services/FileService:f	(Lcom/telesoftas/services/FileService;)I
    //   688: invokevirtual 168	com/telesoftas/hardware/ImagingSignal:a	(I)V
    //   691: aload_0
    //   692: getfield 16	com/telesoftas/services/FileService$ConnectedThread:a	Lcom/telesoftas/services/FileService;
    //   695: invokestatic 129	com/telesoftas/services/FileService:c	(Lcom/telesoftas/services/FileService;)Z
    //   698: ifeq -106 -> 592
    //   701: aload_0
    //   702: getfield 16	com/telesoftas/services/FileService$ConnectedThread:a	Lcom/telesoftas/services/FileService;
    //   705: getfield 171	com/telesoftas/services/FileService:a	Lcom/fridaylab/deeper/communication/DeeperChannel$SignalObserver;
    //   708: aload 50
    //   710: invokeinterface 176 2 0
    //   715: goto -123 -> 592
    //   718: astore 47
    //   720: aload 47
    //   722: astore 44
    //   724: iconst_2
    //   725: istore 42
    //   727: aload 44
    //   729: invokestatic 60	com/crashlytics/android/Crashlytics:a	(Ljava/lang/Throwable;)V
    //   732: iload 41
    //   734: istore 15
    //   736: iload 42
    //   738: istore 9
    //   740: iload 40
    //   742: istore 16
    //   744: iload 27
    //   746: istore 14
    //   748: goto -578 -> 170
    //   751: iload 9
    //   753: istore 42
    //   755: goto -23 -> 732
    //   758: aload_0
    //   759: getfield 23	com/telesoftas/services/FileService$ConnectedThread:d	Ljava/io/BufferedReader;
    //   762: invokevirtual 52	java/io/BufferedReader:close	()V
    //   765: aload_0
    //   766: getfield 21	com/telesoftas/services/FileService$ConnectedThread:c	Ljava/io/InputStream;
    //   769: invokevirtual 55	java/io/InputStream:close	()V
    //   772: return
    //   773: astore 24
    //   775: aload 24
    //   777: invokestatic 60	com/crashlytics/android/Crashlytics:a	(Ljava/lang/Throwable;)V
    //   780: return
    //   781: astore 23
    //   783: aload 23
    //   785: invokestatic 60	com/crashlytics/android/Crashlytics:a	(Ljava/lang/Throwable;)V
    //   788: goto -23 -> 765
    //   791: astore 21
    //   793: aload 21
    //   795: invokestatic 60	com/crashlytics/android/Crashlytics:a	(Ljava/lang/Throwable;)V
    //   798: goto -405 -> 393
    //   801: astore 18
    //   803: aload 18
    //   805: invokestatic 60	com/crashlytics/android/Crashlytics:a	(Ljava/lang/Throwable;)V
    //   808: goto -380 -> 428
    //   811: astore 19
    //   813: aload 19
    //   815: invokestatic 60	com/crashlytics/android/Crashlytics:a	(Ljava/lang/Throwable;)V
    //   818: goto -383 -> 435
    //   821: astore 43
    //   823: aload 43
    //   825: astore 44
    //   827: iload 9
    //   829: istore 42
    //   831: goto -104 -> 727
    //   834: iload 33
    //   836: istore 16
    //   838: iload 28
    //   840: istore 34
    //   842: iload 27
    //   844: istore 35
    //   846: iload 11
    //   848: istore 36
    //   850: goto +95 -> 945
    //   853: iload 16
    //   855: istore 40
    //   857: iload 28
    //   859: istore 41
    //   861: goto +61 -> 922
    //   864: iload 14
    //   866: istore 27
    //   868: iload 15
    //   870: istore 28
    //   872: iconst_0
    //   873: istore 29
    //   875: iload 16
    //   877: ifge -24 -> 853
    //   880: goto -656 -> 224
    //   883: iload 28
    //   885: ifge +7 -> 892
    //   888: iload 29
    //   890: istore 28
    //   892: iload 29
    //   894: iconst_1
    //   895: iadd
    //   896: istore 16
    //   898: iinc 29 1
    //   901: goto -677 -> 224
    //   904: iload 16
    //   906: ifle -8 -> 898
    //   909: iload 16
    //   911: ifle -656 -> 255
    //   914: iload 16
    //   916: istore 40
    //   918: iload 28
    //   920: istore 41
    //   922: iinc 11 1
    //   925: iload 41
    //   927: ifgt -489 -> 438
    //   930: iload 27
    //   932: istore 14
    //   934: iload 41
    //   936: istore 15
    //   938: iload 40
    //   940: istore 16
    //   942: goto -772 -> 170
    //   945: iload 36
    //   947: istore 11
    //   949: iload 32
    //   951: istore 27
    //   953: iload 34
    //   955: istore 37
    //   957: iload 35
    //   959: istore 29
    //   961: iload 37
    //   963: istore 28
    //   965: goto -90 -> 875
    //   968: iload 31
    //   970: iload 27
    //   972: iadd
    //   973: istore 32
    //   975: iload 16
    //   977: istore 33
    //   979: goto -687 -> 292
    //   982: iconst_0
    //   983: istore 46
    //   985: goto -503 -> 482
    // Local variable table:
    //   start	length	slot	name	signature
    //   0	988	0	this	ConnectedThread
    //   22	9	1	i	int
    //   27	9	2	localFileService	FileService
    //   34	85	3	bool1	boolean
    //   48	618	5	localParseResult	com.fridaylab.deeper.communication.ParseResult
    //   67	114	6	l1	long
    //   78	361	8	bool2	boolean
    //   81	747	9	j	int
    //   86	421	10	arrayOfInt1	int[]
    //   89	859	11	k	int
    //   122	3	12	localException1	Exception
    //   159	285	13	arrayOfChar	char[]
    //   162	771	14	m	int
    //   165	772	15	n	int
    //   168	808	16	i1	int
    //   419	17	17	localObject1	java.lang.Object
    //   801	3	18	localException2	Exception
    //   811	3	19	localException3	Exception
    //   379	3	20	localIOException	java.io.IOException
    //   791	3	21	localException4	Exception
    //   401	3	22	localException5	Exception
    //   781	3	23	localException6	Exception
    //   773	3	24	localException7	Exception
    //   186	408	25	l2	long
    //   226	747	27	i2	int
    //   286	678	28	i3	int
    //   224	736	29	i4	int
    //   236	14	30	i5	int
    //   272	701	31	i6	int
    //   282	692	32	i7	int
    //   290	688	33	i8	int
    //   301	653	34	i9	int
    //   364	594	35	i10	int
    //   361	585	36	i11	int
    //   955	7	37	i12	int
    //   369	3	38	localException8	Exception
    //   409	3	39	localException9	Exception
    //   466	473	40	i13	int
    //   445	490	41	i14	int
    //   725	105	42	i15	int
    //   821	3	43	localInterruptedException1	java.lang.InterruptedException
    //   722	104	44	localObject2	java.lang.Object
    //   451	220	45	arrayOfByte	byte[]
    //   480	504	46	b1	byte
    //   718	3	47	localInterruptedException2	java.lang.InterruptedException
    //   619	54	48	arrayOfInt2	int[]
    //   632	32	49	f1	float
    //   677	32	50	localDeeperRawDataPacket	com.telesoftas.hardware.DeeperRawDataPacket
    //   513	32	51	f2	float
    //   554	32	52	localDeeperFishDataPacket	com.telesoftas.hardware.DeeperFishDataPacket
    // Exception table:
    //   from	to	target	type
    //   91	109	122	java/lang/Exception
    //   303	310	369	java/lang/Exception
    //   170	188	379	java/io/IOException
    //   193	208	379	java/io/IOException
    //   231	238	379	java/io/IOException
    //   255	274	379	java/io/IOException
    //   303	310	379	java/io/IOException
    //   310	317	379	java/io/IOException
    //   317	360	379	java/io/IOException
    //   371	376	379	java/io/IOException
    //   411	416	379	java/io/IOException
    //   443	453	379	java/io/IOException
    //   482	515	379	java/io/IOException
    //   540	592	379	java/io/IOException
    //   592	598	379	java/io/IOException
    //   616	634	379	java/io/IOException
    //   659	715	379	java/io/IOException
    //   727	732	379	java/io/IOException
    //   393	400	401	java/lang/Exception
    //   310	317	409	java/lang/Exception
    //   170	188	419	finally
    //   193	208	419	finally
    //   231	238	419	finally
    //   255	274	419	finally
    //   303	310	419	finally
    //   310	317	419	finally
    //   317	360	419	finally
    //   371	376	419	finally
    //   381	386	419	finally
    //   411	416	419	finally
    //   443	453	419	finally
    //   482	515	419	finally
    //   540	592	419	finally
    //   592	598	419	finally
    //   616	634	419	finally
    //   659	715	419	finally
    //   727	732	419	finally
    //   482	515	718	java/lang/InterruptedException
    //   540	592	718	java/lang/InterruptedException
    //   592	598	718	java/lang/InterruptedException
    //   616	634	718	java/lang/InterruptedException
    //   659	715	718	java/lang/InterruptedException
    //   765	772	773	java/lang/Exception
    //   758	765	781	java/lang/Exception
    //   386	393	791	java/lang/Exception
    //   421	428	801	java/lang/Exception
    //   428	435	811	java/lang/Exception
    //   443	453	821	java/lang/InterruptedException
  }
}


/* Location:           C:\DISKD\fishfinder\apktool-install-windows-r05-ibot\classes_dex2jar.jar
 * Qualified Name:     com.telesoftas.services.FileService.ConnectedThread
 * JD-Core Version:    0.7.0.1
 */