package com.google.android.gms.maps.internal;

import android.os.IBinder;
import android.os.Parcel;
import com.google.android.gms.maps.model.GroundOverlayOptions;
import com.google.android.gms.maps.model.MarkerOptions;
import com.google.android.gms.maps.model.internal.c;
import com.google.android.gms.maps.model.internal.e;
import com.google.android.gms.maps.model.internal.i;
import com.google.android.gms.maps.model.internal.i.a;
import com.google.android.gms.maps.model.internal.j;
import com.google.android.gms.maps.model.internal.j.a;
import com.google.android.gms.maps.model.internal.l;
import com.google.android.gms.maps.model.internal.l.a;
import com.google.android.gms.maps.model.internal.p;

class IGoogleMapDelegate$a$a
  implements IGoogleMapDelegate
{
  private IBinder a;
  
  IGoogleMapDelegate$a$a(IBinder paramIBinder)
  {
    this.a = paramIBinder;
  }
  
  /* Error */
  public com.google.android.gms.maps.model.CameraPosition a()
  {
    // Byte code:
    //   0: invokestatic 22	android/os/Parcel:obtain	()Landroid/os/Parcel;
    //   3: astore_1
    //   4: invokestatic 22	android/os/Parcel:obtain	()Landroid/os/Parcel;
    //   7: astore_2
    //   8: aload_1
    //   9: ldc 24
    //   11: invokevirtual 28	android/os/Parcel:writeInterfaceToken	(Ljava/lang/String;)V
    //   14: aload_0
    //   15: getfield 15	com/google/android/gms/maps/internal/IGoogleMapDelegate$a$a:a	Landroid/os/IBinder;
    //   18: iconst_1
    //   19: aload_1
    //   20: aload_2
    //   21: iconst_0
    //   22: invokeinterface 34 5 0
    //   27: pop
    //   28: aload_2
    //   29: invokevirtual 37	android/os/Parcel:readException	()V
    //   32: aload_2
    //   33: invokevirtual 41	android/os/Parcel:readInt	()I
    //   36: ifeq +27 -> 63
    //   39: getstatic 47	com/google/android/gms/maps/model/CameraPosition:CREATOR	Lcom/google/android/gms/maps/model/a;
    //   42: aload_2
    //   43: invokevirtual 52	com/google/android/gms/maps/model/a:a	(Landroid/os/Parcel;)Lcom/google/android/gms/maps/model/CameraPosition;
    //   46: astore 6
    //   48: aload 6
    //   50: astore 5
    //   52: aload_2
    //   53: invokevirtual 55	android/os/Parcel:recycle	()V
    //   56: aload_1
    //   57: invokevirtual 55	android/os/Parcel:recycle	()V
    //   60: aload 5
    //   62: areturn
    //   63: aconst_null
    //   64: astore 5
    //   66: goto -14 -> 52
    //   69: astore_3
    //   70: aload_2
    //   71: invokevirtual 55	android/os/Parcel:recycle	()V
    //   74: aload_1
    //   75: invokevirtual 55	android/os/Parcel:recycle	()V
    //   78: aload_3
    //   79: athrow
    // Local variable table:
    //   start	length	slot	name	signature
    //   0	80	0	this	a
    //   3	72	1	localParcel1	Parcel
    //   7	64	2	localParcel2	Parcel
    //   69	10	3	localObject	Object
    //   50	15	5	localCameraPosition1	com.google.android.gms.maps.model.CameraPosition
    //   46	3	6	localCameraPosition2	com.google.android.gms.maps.model.CameraPosition
    // Exception table:
    //   from	to	target	type
    //   8	48	69	finally
  }
  
  /* Error */
  public com.google.android.gms.maps.model.internal.IPolylineDelegate a(com.google.android.gms.maps.model.PolylineOptions paramPolylineOptions)
  {
    // Byte code:
    //   0: invokestatic 22	android/os/Parcel:obtain	()Landroid/os/Parcel;
    //   3: astore_2
    //   4: invokestatic 22	android/os/Parcel:obtain	()Landroid/os/Parcel;
    //   7: astore_3
    //   8: aload_2
    //   9: ldc 24
    //   11: invokevirtual 28	android/os/Parcel:writeInterfaceToken	(Ljava/lang/String;)V
    //   14: aload_1
    //   15: ifnull +53 -> 68
    //   18: aload_2
    //   19: iconst_1
    //   20: invokevirtual 60	android/os/Parcel:writeInt	(I)V
    //   23: aload_1
    //   24: aload_2
    //   25: iconst_0
    //   26: invokevirtual 66	com/google/android/gms/maps/model/PolylineOptions:writeToParcel	(Landroid/os/Parcel;I)V
    //   29: aload_0
    //   30: getfield 15	com/google/android/gms/maps/internal/IGoogleMapDelegate$a$a:a	Landroid/os/IBinder;
    //   33: bipush 9
    //   35: aload_2
    //   36: aload_3
    //   37: iconst_0
    //   38: invokeinterface 34 5 0
    //   43: pop
    //   44: aload_3
    //   45: invokevirtual 37	android/os/Parcel:readException	()V
    //   48: aload_3
    //   49: invokevirtual 70	android/os/Parcel:readStrongBinder	()Landroid/os/IBinder;
    //   52: invokestatic 75	com/google/android/gms/maps/model/internal/IPolylineDelegate$a:a	(Landroid/os/IBinder;)Lcom/google/android/gms/maps/model/internal/IPolylineDelegate;
    //   55: astore 6
    //   57: aload_3
    //   58: invokevirtual 55	android/os/Parcel:recycle	()V
    //   61: aload_2
    //   62: invokevirtual 55	android/os/Parcel:recycle	()V
    //   65: aload 6
    //   67: areturn
    //   68: aload_2
    //   69: iconst_0
    //   70: invokevirtual 60	android/os/Parcel:writeInt	(I)V
    //   73: goto -44 -> 29
    //   76: astore 4
    //   78: aload_3
    //   79: invokevirtual 55	android/os/Parcel:recycle	()V
    //   82: aload_2
    //   83: invokevirtual 55	android/os/Parcel:recycle	()V
    //   86: aload 4
    //   88: athrow
    // Local variable table:
    //   start	length	slot	name	signature
    //   0	89	0	this	a
    //   0	89	1	paramPolylineOptions	com.google.android.gms.maps.model.PolylineOptions
    //   3	80	2	localParcel1	Parcel
    //   7	72	3	localParcel2	Parcel
    //   76	11	4	localObject	Object
    //   55	11	6	localIPolylineDelegate	com.google.android.gms.maps.model.internal.IPolylineDelegate
    // Exception table:
    //   from	to	target	type
    //   8	14	76	finally
    //   18	29	76	finally
    //   29	57	76	finally
    //   68	73	76	finally
  }
  
  /* Error */
  public com.google.android.gms.maps.model.internal.h a(com.google.android.gms.maps.model.CircleOptions paramCircleOptions)
  {
    // Byte code:
    //   0: invokestatic 22	android/os/Parcel:obtain	()Landroid/os/Parcel;
    //   3: astore_2
    //   4: invokestatic 22	android/os/Parcel:obtain	()Landroid/os/Parcel;
    //   7: astore_3
    //   8: aload_2
    //   9: ldc 24
    //   11: invokevirtual 28	android/os/Parcel:writeInterfaceToken	(Ljava/lang/String;)V
    //   14: aload_1
    //   15: ifnull +53 -> 68
    //   18: aload_2
    //   19: iconst_1
    //   20: invokevirtual 60	android/os/Parcel:writeInt	(I)V
    //   23: aload_1
    //   24: aload_2
    //   25: iconst_0
    //   26: invokevirtual 79	com/google/android/gms/maps/model/CircleOptions:writeToParcel	(Landroid/os/Parcel;I)V
    //   29: aload_0
    //   30: getfield 15	com/google/android/gms/maps/internal/IGoogleMapDelegate$a$a:a	Landroid/os/IBinder;
    //   33: bipush 35
    //   35: aload_2
    //   36: aload_3
    //   37: iconst_0
    //   38: invokeinterface 34 5 0
    //   43: pop
    //   44: aload_3
    //   45: invokevirtual 37	android/os/Parcel:readException	()V
    //   48: aload_3
    //   49: invokevirtual 70	android/os/Parcel:readStrongBinder	()Landroid/os/IBinder;
    //   52: invokestatic 84	com/google/android/gms/maps/model/internal/h$a:a	(Landroid/os/IBinder;)Lcom/google/android/gms/maps/model/internal/h;
    //   55: astore 6
    //   57: aload_3
    //   58: invokevirtual 55	android/os/Parcel:recycle	()V
    //   61: aload_2
    //   62: invokevirtual 55	android/os/Parcel:recycle	()V
    //   65: aload 6
    //   67: areturn
    //   68: aload_2
    //   69: iconst_0
    //   70: invokevirtual 60	android/os/Parcel:writeInt	(I)V
    //   73: goto -44 -> 29
    //   76: astore 4
    //   78: aload_3
    //   79: invokevirtual 55	android/os/Parcel:recycle	()V
    //   82: aload_2
    //   83: invokevirtual 55	android/os/Parcel:recycle	()V
    //   86: aload 4
    //   88: athrow
    // Local variable table:
    //   start	length	slot	name	signature
    //   0	89	0	this	a
    //   0	89	1	paramCircleOptions	com.google.android.gms.maps.model.CircleOptions
    //   3	80	2	localParcel1	Parcel
    //   7	72	3	localParcel2	Parcel
    //   76	11	4	localObject	Object
    //   55	11	6	localh	com.google.android.gms.maps.model.internal.h
    // Exception table:
    //   from	to	target	type
    //   8	14	76	finally
    //   18	29	76	finally
    //   29	57	76	finally
    //   68	73	76	finally
  }
  
  /* Error */
  public i a(GroundOverlayOptions paramGroundOverlayOptions)
  {
    // Byte code:
    //   0: invokestatic 22	android/os/Parcel:obtain	()Landroid/os/Parcel;
    //   3: astore_2
    //   4: invokestatic 22	android/os/Parcel:obtain	()Landroid/os/Parcel;
    //   7: astore_3
    //   8: aload_2
    //   9: ldc 24
    //   11: invokevirtual 28	android/os/Parcel:writeInterfaceToken	(Ljava/lang/String;)V
    //   14: aload_1
    //   15: ifnull +53 -> 68
    //   18: aload_2
    //   19: iconst_1
    //   20: invokevirtual 60	android/os/Parcel:writeInt	(I)V
    //   23: aload_1
    //   24: aload_2
    //   25: iconst_0
    //   26: invokevirtual 88	com/google/android/gms/maps/model/GroundOverlayOptions:writeToParcel	(Landroid/os/Parcel;I)V
    //   29: aload_0
    //   30: getfield 15	com/google/android/gms/maps/internal/IGoogleMapDelegate$a$a:a	Landroid/os/IBinder;
    //   33: bipush 12
    //   35: aload_2
    //   36: aload_3
    //   37: iconst_0
    //   38: invokeinterface 34 5 0
    //   43: pop
    //   44: aload_3
    //   45: invokevirtual 37	android/os/Parcel:readException	()V
    //   48: aload_3
    //   49: invokevirtual 70	android/os/Parcel:readStrongBinder	()Landroid/os/IBinder;
    //   52: invokestatic 93	com/google/android/gms/maps/model/internal/i$a:a	(Landroid/os/IBinder;)Lcom/google/android/gms/maps/model/internal/i;
    //   55: astore 6
    //   57: aload_3
    //   58: invokevirtual 55	android/os/Parcel:recycle	()V
    //   61: aload_2
    //   62: invokevirtual 55	android/os/Parcel:recycle	()V
    //   65: aload 6
    //   67: areturn
    //   68: aload_2
    //   69: iconst_0
    //   70: invokevirtual 60	android/os/Parcel:writeInt	(I)V
    //   73: goto -44 -> 29
    //   76: astore 4
    //   78: aload_3
    //   79: invokevirtual 55	android/os/Parcel:recycle	()V
    //   82: aload_2
    //   83: invokevirtual 55	android/os/Parcel:recycle	()V
    //   86: aload 4
    //   88: athrow
    // Local variable table:
    //   start	length	slot	name	signature
    //   0	89	0	this	a
    //   0	89	1	paramGroundOverlayOptions	GroundOverlayOptions
    //   3	80	2	localParcel1	Parcel
    //   7	72	3	localParcel2	Parcel
    //   76	11	4	localObject	Object
    //   55	11	6	locali	i
    // Exception table:
    //   from	to	target	type
    //   8	14	76	finally
    //   18	29	76	finally
    //   29	57	76	finally
    //   68	73	76	finally
  }
  
  public i a(GroundOverlayOptions paramGroundOverlayOptions, e parame)
  {
    Parcel localParcel1 = Parcel.obtain();
    Parcel localParcel2 = Parcel.obtain();
    for (;;)
    {
      try
      {
        localParcel1.writeInterfaceToken("com.google.android.gms.maps.internal.IGoogleMapDelegate");
        if (paramGroundOverlayOptions != null)
        {
          localParcel1.writeInt(1);
          paramGroundOverlayOptions.writeToParcel(localParcel1, 0);
          if (parame != null)
          {
            localParcel1.writeInt(1);
            parame.writeToParcel(localParcel1, 0);
            this.a.transact(70, localParcel1, localParcel2, 0);
            localParcel2.readException();
            i locali = i.a.a(localParcel2.readStrongBinder());
            return locali;
          }
        }
        else
        {
          localParcel1.writeInt(0);
          continue;
        }
        localParcel1.writeInt(0);
      }
      finally
      {
        localParcel2.recycle();
        localParcel1.recycle();
      }
    }
  }
  
  /* Error */
  public l a(MarkerOptions paramMarkerOptions)
  {
    // Byte code:
    //   0: invokestatic 22	android/os/Parcel:obtain	()Landroid/os/Parcel;
    //   3: astore_2
    //   4: invokestatic 22	android/os/Parcel:obtain	()Landroid/os/Parcel;
    //   7: astore_3
    //   8: aload_2
    //   9: ldc 24
    //   11: invokevirtual 28	android/os/Parcel:writeInterfaceToken	(Ljava/lang/String;)V
    //   14: aload_1
    //   15: ifnull +53 -> 68
    //   18: aload_2
    //   19: iconst_1
    //   20: invokevirtual 60	android/os/Parcel:writeInt	(I)V
    //   23: aload_1
    //   24: aload_2
    //   25: iconst_0
    //   26: invokevirtual 101	com/google/android/gms/maps/model/MarkerOptions:writeToParcel	(Landroid/os/Parcel;I)V
    //   29: aload_0
    //   30: getfield 15	com/google/android/gms/maps/internal/IGoogleMapDelegate$a$a:a	Landroid/os/IBinder;
    //   33: bipush 11
    //   35: aload_2
    //   36: aload_3
    //   37: iconst_0
    //   38: invokeinterface 34 5 0
    //   43: pop
    //   44: aload_3
    //   45: invokevirtual 37	android/os/Parcel:readException	()V
    //   48: aload_3
    //   49: invokevirtual 70	android/os/Parcel:readStrongBinder	()Landroid/os/IBinder;
    //   52: invokestatic 106	com/google/android/gms/maps/model/internal/l$a:a	(Landroid/os/IBinder;)Lcom/google/android/gms/maps/model/internal/l;
    //   55: astore 6
    //   57: aload_3
    //   58: invokevirtual 55	android/os/Parcel:recycle	()V
    //   61: aload_2
    //   62: invokevirtual 55	android/os/Parcel:recycle	()V
    //   65: aload 6
    //   67: areturn
    //   68: aload_2
    //   69: iconst_0
    //   70: invokevirtual 60	android/os/Parcel:writeInt	(I)V
    //   73: goto -44 -> 29
    //   76: astore 4
    //   78: aload_3
    //   79: invokevirtual 55	android/os/Parcel:recycle	()V
    //   82: aload_2
    //   83: invokevirtual 55	android/os/Parcel:recycle	()V
    //   86: aload 4
    //   88: athrow
    // Local variable table:
    //   start	length	slot	name	signature
    //   0	89	0	this	a
    //   0	89	1	paramMarkerOptions	MarkerOptions
    //   3	80	2	localParcel1	Parcel
    //   7	72	3	localParcel2	Parcel
    //   76	11	4	localObject	Object
    //   55	11	6	locall	l
    // Exception table:
    //   from	to	target	type
    //   8	14	76	finally
    //   18	29	76	finally
    //   29	57	76	finally
    //   68	73	76	finally
  }
  
  public l a(MarkerOptions paramMarkerOptions, p paramp)
  {
    Parcel localParcel1 = Parcel.obtain();
    Parcel localParcel2 = Parcel.obtain();
    for (;;)
    {
      try
      {
        localParcel1.writeInterfaceToken("com.google.android.gms.maps.internal.IGoogleMapDelegate");
        if (paramMarkerOptions != null)
        {
          localParcel1.writeInt(1);
          paramMarkerOptions.writeToParcel(localParcel1, 0);
          if (paramp != null)
          {
            localParcel1.writeInt(1);
            paramp.writeToParcel(localParcel1, 0);
            this.a.transact(68, localParcel1, localParcel2, 0);
            localParcel2.readException();
            l locall = l.a.a(localParcel2.readStrongBinder());
            return locall;
          }
        }
        else
        {
          localParcel1.writeInt(0);
          continue;
        }
        localParcel1.writeInt(0);
      }
      finally
      {
        localParcel2.recycle();
        localParcel1.recycle();
      }
    }
  }
  
  /* Error */
  public com.google.android.gms.maps.model.internal.m a(com.google.android.gms.maps.model.PolygonOptions paramPolygonOptions)
  {
    // Byte code:
    //   0: invokestatic 22	android/os/Parcel:obtain	()Landroid/os/Parcel;
    //   3: astore_2
    //   4: invokestatic 22	android/os/Parcel:obtain	()Landroid/os/Parcel;
    //   7: astore_3
    //   8: aload_2
    //   9: ldc 24
    //   11: invokevirtual 28	android/os/Parcel:writeInterfaceToken	(Ljava/lang/String;)V
    //   14: aload_1
    //   15: ifnull +53 -> 68
    //   18: aload_2
    //   19: iconst_1
    //   20: invokevirtual 60	android/os/Parcel:writeInt	(I)V
    //   23: aload_1
    //   24: aload_2
    //   25: iconst_0
    //   26: invokevirtual 114	com/google/android/gms/maps/model/PolygonOptions:writeToParcel	(Landroid/os/Parcel;I)V
    //   29: aload_0
    //   30: getfield 15	com/google/android/gms/maps/internal/IGoogleMapDelegate$a$a:a	Landroid/os/IBinder;
    //   33: bipush 10
    //   35: aload_2
    //   36: aload_3
    //   37: iconst_0
    //   38: invokeinterface 34 5 0
    //   43: pop
    //   44: aload_3
    //   45: invokevirtual 37	android/os/Parcel:readException	()V
    //   48: aload_3
    //   49: invokevirtual 70	android/os/Parcel:readStrongBinder	()Landroid/os/IBinder;
    //   52: invokestatic 119	com/google/android/gms/maps/model/internal/m$a:a	(Landroid/os/IBinder;)Lcom/google/android/gms/maps/model/internal/m;
    //   55: astore 6
    //   57: aload_3
    //   58: invokevirtual 55	android/os/Parcel:recycle	()V
    //   61: aload_2
    //   62: invokevirtual 55	android/os/Parcel:recycle	()V
    //   65: aload 6
    //   67: areturn
    //   68: aload_2
    //   69: iconst_0
    //   70: invokevirtual 60	android/os/Parcel:writeInt	(I)V
    //   73: goto -44 -> 29
    //   76: astore 4
    //   78: aload_3
    //   79: invokevirtual 55	android/os/Parcel:recycle	()V
    //   82: aload_2
    //   83: invokevirtual 55	android/os/Parcel:recycle	()V
    //   86: aload 4
    //   88: athrow
    // Local variable table:
    //   start	length	slot	name	signature
    //   0	89	0	this	a
    //   0	89	1	paramPolygonOptions	com.google.android.gms.maps.model.PolygonOptions
    //   3	80	2	localParcel1	Parcel
    //   7	72	3	localParcel2	Parcel
    //   76	11	4	localObject	Object
    //   55	11	6	localm	com.google.android.gms.maps.model.internal.m
    // Exception table:
    //   from	to	target	type
    //   8	14	76	finally
    //   18	29	76	finally
    //   29	57	76	finally
    //   68	73	76	finally
  }
  
  /* Error */
  public com.google.android.gms.maps.model.internal.n a(com.google.android.gms.maps.model.TileOverlayOptions paramTileOverlayOptions)
  {
    // Byte code:
    //   0: invokestatic 22	android/os/Parcel:obtain	()Landroid/os/Parcel;
    //   3: astore_2
    //   4: invokestatic 22	android/os/Parcel:obtain	()Landroid/os/Parcel;
    //   7: astore_3
    //   8: aload_2
    //   9: ldc 24
    //   11: invokevirtual 28	android/os/Parcel:writeInterfaceToken	(Ljava/lang/String;)V
    //   14: aload_1
    //   15: ifnull +53 -> 68
    //   18: aload_2
    //   19: iconst_1
    //   20: invokevirtual 60	android/os/Parcel:writeInt	(I)V
    //   23: aload_1
    //   24: aload_2
    //   25: iconst_0
    //   26: invokevirtual 123	com/google/android/gms/maps/model/TileOverlayOptions:writeToParcel	(Landroid/os/Parcel;I)V
    //   29: aload_0
    //   30: getfield 15	com/google/android/gms/maps/internal/IGoogleMapDelegate$a$a:a	Landroid/os/IBinder;
    //   33: bipush 13
    //   35: aload_2
    //   36: aload_3
    //   37: iconst_0
    //   38: invokeinterface 34 5 0
    //   43: pop
    //   44: aload_3
    //   45: invokevirtual 37	android/os/Parcel:readException	()V
    //   48: aload_3
    //   49: invokevirtual 70	android/os/Parcel:readStrongBinder	()Landroid/os/IBinder;
    //   52: invokestatic 128	com/google/android/gms/maps/model/internal/n$a:a	(Landroid/os/IBinder;)Lcom/google/android/gms/maps/model/internal/n;
    //   55: astore 6
    //   57: aload_3
    //   58: invokevirtual 55	android/os/Parcel:recycle	()V
    //   61: aload_2
    //   62: invokevirtual 55	android/os/Parcel:recycle	()V
    //   65: aload 6
    //   67: areturn
    //   68: aload_2
    //   69: iconst_0
    //   70: invokevirtual 60	android/os/Parcel:writeInt	(I)V
    //   73: goto -44 -> 29
    //   76: astore 4
    //   78: aload_3
    //   79: invokevirtual 55	android/os/Parcel:recycle	()V
    //   82: aload_2
    //   83: invokevirtual 55	android/os/Parcel:recycle	()V
    //   86: aload 4
    //   88: athrow
    // Local variable table:
    //   start	length	slot	name	signature
    //   0	89	0	this	a
    //   0	89	1	paramTileOverlayOptions	com.google.android.gms.maps.model.TileOverlayOptions
    //   3	80	2	localParcel1	Parcel
    //   7	72	3	localParcel2	Parcel
    //   76	11	4	localObject	Object
    //   55	11	6	localn	com.google.android.gms.maps.model.internal.n
    // Exception table:
    //   from	to	target	type
    //   8	14	76	finally
    //   18	29	76	finally
    //   29	57	76	finally
    //   68	73	76	finally
  }
  
  public void a(int paramInt)
  {
    Parcel localParcel1 = Parcel.obtain();
    Parcel localParcel2 = Parcel.obtain();
    try
    {
      localParcel1.writeInterfaceToken("com.google.android.gms.maps.internal.IGoogleMapDelegate");
      localParcel1.writeInt(paramInt);
      this.a.transact(16, localParcel1, localParcel2, 0);
      localParcel2.readException();
      return;
    }
    finally
    {
      localParcel2.recycle();
      localParcel1.recycle();
    }
  }
  
  public void a(int paramInt1, int paramInt2, int paramInt3, int paramInt4)
  {
    Parcel localParcel1 = Parcel.obtain();
    Parcel localParcel2 = Parcel.obtain();
    try
    {
      localParcel1.writeInterfaceToken("com.google.android.gms.maps.internal.IGoogleMapDelegate");
      localParcel1.writeInt(paramInt1);
      localParcel1.writeInt(paramInt2);
      localParcel1.writeInt(paramInt3);
      localParcel1.writeInt(paramInt4);
      this.a.transact(39, localParcel1, localParcel2, 0);
      localParcel2.readException();
      return;
    }
    finally
    {
      localParcel2.recycle();
      localParcel1.recycle();
    }
  }
  
  /* Error */
  public void a(android.os.Bundle paramBundle)
  {
    // Byte code:
    //   0: invokestatic 22	android/os/Parcel:obtain	()Landroid/os/Parcel;
    //   3: astore_2
    //   4: invokestatic 22	android/os/Parcel:obtain	()Landroid/os/Parcel;
    //   7: astore_3
    //   8: aload_2
    //   9: ldc 24
    //   11: invokevirtual 28	android/os/Parcel:writeInterfaceToken	(Ljava/lang/String;)V
    //   14: aload_1
    //   15: ifnull +42 -> 57
    //   18: aload_2
    //   19: iconst_1
    //   20: invokevirtual 60	android/os/Parcel:writeInt	(I)V
    //   23: aload_1
    //   24: aload_2
    //   25: iconst_0
    //   26: invokevirtual 133	android/os/Bundle:writeToParcel	(Landroid/os/Parcel;I)V
    //   29: aload_0
    //   30: getfield 15	com/google/android/gms/maps/internal/IGoogleMapDelegate$a$a:a	Landroid/os/IBinder;
    //   33: bipush 54
    //   35: aload_2
    //   36: aload_3
    //   37: iconst_0
    //   38: invokeinterface 34 5 0
    //   43: pop
    //   44: aload_3
    //   45: invokevirtual 37	android/os/Parcel:readException	()V
    //   48: aload_3
    //   49: invokevirtual 55	android/os/Parcel:recycle	()V
    //   52: aload_2
    //   53: invokevirtual 55	android/os/Parcel:recycle	()V
    //   56: return
    //   57: aload_2
    //   58: iconst_0
    //   59: invokevirtual 60	android/os/Parcel:writeInt	(I)V
    //   62: goto -33 -> 29
    //   65: astore 4
    //   67: aload_3
    //   68: invokevirtual 55	android/os/Parcel:recycle	()V
    //   71: aload_2
    //   72: invokevirtual 55	android/os/Parcel:recycle	()V
    //   75: aload 4
    //   77: athrow
    // Local variable table:
    //   start	length	slot	name	signature
    //   0	78	0	this	a
    //   0	78	1	paramBundle	android.os.Bundle
    //   3	69	2	localParcel1	Parcel
    //   7	61	3	localParcel2	Parcel
    //   65	11	4	localObject	Object
    // Exception table:
    //   from	to	target	type
    //   8	14	65	finally
    //   18	29	65	finally
    //   29	48	65	finally
    //   57	62	65	finally
  }
  
  /* Error */
  public void a(com.google.android.gms.dynamic.d paramd)
  {
    // Byte code:
    //   0: invokestatic 22	android/os/Parcel:obtain	()Landroid/os/Parcel;
    //   3: astore_2
    //   4: invokestatic 22	android/os/Parcel:obtain	()Landroid/os/Parcel;
    //   7: astore_3
    //   8: aload_2
    //   9: ldc 24
    //   11: invokevirtual 28	android/os/Parcel:writeInterfaceToken	(Ljava/lang/String;)V
    //   14: aload_1
    //   15: ifnull +44 -> 59
    //   18: aload_1
    //   19: invokeinterface 139 1 0
    //   24: astore 5
    //   26: aload_2
    //   27: aload 5
    //   29: invokevirtual 142	android/os/Parcel:writeStrongBinder	(Landroid/os/IBinder;)V
    //   32: aload_0
    //   33: getfield 15	com/google/android/gms/maps/internal/IGoogleMapDelegate$a$a:a	Landroid/os/IBinder;
    //   36: iconst_4
    //   37: aload_2
    //   38: aload_3
    //   39: iconst_0
    //   40: invokeinterface 34 5 0
    //   45: pop
    //   46: aload_3
    //   47: invokevirtual 37	android/os/Parcel:readException	()V
    //   50: aload_3
    //   51: invokevirtual 55	android/os/Parcel:recycle	()V
    //   54: aload_2
    //   55: invokevirtual 55	android/os/Parcel:recycle	()V
    //   58: return
    //   59: aconst_null
    //   60: astore 5
    //   62: goto -36 -> 26
    //   65: astore 4
    //   67: aload_3
    //   68: invokevirtual 55	android/os/Parcel:recycle	()V
    //   71: aload_2
    //   72: invokevirtual 55	android/os/Parcel:recycle	()V
    //   75: aload 4
    //   77: athrow
    // Local variable table:
    //   start	length	slot	name	signature
    //   0	78	0	this	a
    //   0	78	1	paramd	com.google.android.gms.dynamic.d
    //   3	69	2	localParcel1	Parcel
    //   7	61	3	localParcel2	Parcel
    //   65	11	4	localObject	Object
    //   24	37	5	localIBinder	IBinder
    // Exception table:
    //   from	to	target	type
    //   8	14	65	finally
    //   18	26	65	finally
    //   26	50	65	finally
  }
  
  /* Error */
  public void a(com.google.android.gms.dynamic.d paramd, int paramInt, b paramb)
  {
    // Byte code:
    //   0: invokestatic 22	android/os/Parcel:obtain	()Landroid/os/Parcel;
    //   3: astore 4
    //   5: invokestatic 22	android/os/Parcel:obtain	()Landroid/os/Parcel;
    //   8: astore 5
    //   10: aload 4
    //   12: ldc 24
    //   14: invokevirtual 28	android/os/Parcel:writeInterfaceToken	(Ljava/lang/String;)V
    //   17: aload_1
    //   18: ifnull +79 -> 97
    //   21: aload_1
    //   22: invokeinterface 139 1 0
    //   27: astore 7
    //   29: aload 4
    //   31: aload 7
    //   33: invokevirtual 142	android/os/Parcel:writeStrongBinder	(Landroid/os/IBinder;)V
    //   36: aload 4
    //   38: iload_2
    //   39: invokevirtual 60	android/os/Parcel:writeInt	(I)V
    //   42: aconst_null
    //   43: astore 8
    //   45: aload_3
    //   46: ifnull +11 -> 57
    //   49: aload_3
    //   50: invokeinterface 146 1 0
    //   55: astore 8
    //   57: aload 4
    //   59: aload 8
    //   61: invokevirtual 142	android/os/Parcel:writeStrongBinder	(Landroid/os/IBinder;)V
    //   64: aload_0
    //   65: getfield 15	com/google/android/gms/maps/internal/IGoogleMapDelegate$a$a:a	Landroid/os/IBinder;
    //   68: bipush 7
    //   70: aload 4
    //   72: aload 5
    //   74: iconst_0
    //   75: invokeinterface 34 5 0
    //   80: pop
    //   81: aload 5
    //   83: invokevirtual 37	android/os/Parcel:readException	()V
    //   86: aload 5
    //   88: invokevirtual 55	android/os/Parcel:recycle	()V
    //   91: aload 4
    //   93: invokevirtual 55	android/os/Parcel:recycle	()V
    //   96: return
    //   97: aconst_null
    //   98: astore 7
    //   100: goto -71 -> 29
    //   103: astore 6
    //   105: aload 5
    //   107: invokevirtual 55	android/os/Parcel:recycle	()V
    //   110: aload 4
    //   112: invokevirtual 55	android/os/Parcel:recycle	()V
    //   115: aload 6
    //   117: athrow
    // Local variable table:
    //   start	length	slot	name	signature
    //   0	118	0	this	a
    //   0	118	1	paramd	com.google.android.gms.dynamic.d
    //   0	118	2	paramInt	int
    //   0	118	3	paramb	b
    //   3	108	4	localParcel1	Parcel
    //   8	98	5	localParcel2	Parcel
    //   103	13	6	localObject	Object
    //   27	72	7	localIBinder1	IBinder
    //   43	17	8	localIBinder2	IBinder
    // Exception table:
    //   from	to	target	type
    //   10	17	103	finally
    //   21	29	103	finally
    //   29	42	103	finally
    //   49	57	103	finally
    //   57	86	103	finally
  }
  
  /* Error */
  public void a(com.google.android.gms.dynamic.d paramd, b paramb)
  {
    // Byte code:
    //   0: invokestatic 22	android/os/Parcel:obtain	()Landroid/os/Parcel;
    //   3: astore_3
    //   4: invokestatic 22	android/os/Parcel:obtain	()Landroid/os/Parcel;
    //   7: astore 4
    //   9: aload_3
    //   10: ldc 24
    //   12: invokevirtual 28	android/os/Parcel:writeInterfaceToken	(Ljava/lang/String;)V
    //   15: aload_1
    //   16: ifnull +69 -> 85
    //   19: aload_1
    //   20: invokeinterface 139 1 0
    //   25: astore 6
    //   27: aload_3
    //   28: aload 6
    //   30: invokevirtual 142	android/os/Parcel:writeStrongBinder	(Landroid/os/IBinder;)V
    //   33: aconst_null
    //   34: astore 7
    //   36: aload_2
    //   37: ifnull +11 -> 48
    //   40: aload_2
    //   41: invokeinterface 146 1 0
    //   46: astore 7
    //   48: aload_3
    //   49: aload 7
    //   51: invokevirtual 142	android/os/Parcel:writeStrongBinder	(Landroid/os/IBinder;)V
    //   54: aload_0
    //   55: getfield 15	com/google/android/gms/maps/internal/IGoogleMapDelegate$a$a:a	Landroid/os/IBinder;
    //   58: bipush 6
    //   60: aload_3
    //   61: aload 4
    //   63: iconst_0
    //   64: invokeinterface 34 5 0
    //   69: pop
    //   70: aload 4
    //   72: invokevirtual 37	android/os/Parcel:readException	()V
    //   75: aload 4
    //   77: invokevirtual 55	android/os/Parcel:recycle	()V
    //   80: aload_3
    //   81: invokevirtual 55	android/os/Parcel:recycle	()V
    //   84: return
    //   85: aconst_null
    //   86: astore 6
    //   88: goto -61 -> 27
    //   91: astore 5
    //   93: aload 4
    //   95: invokevirtual 55	android/os/Parcel:recycle	()V
    //   98: aload_3
    //   99: invokevirtual 55	android/os/Parcel:recycle	()V
    //   102: aload 5
    //   104: athrow
    // Local variable table:
    //   start	length	slot	name	signature
    //   0	105	0	this	a
    //   0	105	1	paramd	com.google.android.gms.dynamic.d
    //   0	105	2	paramb	b
    //   3	96	3	localParcel1	Parcel
    //   7	87	4	localParcel2	Parcel
    //   91	12	5	localObject	Object
    //   25	62	6	localIBinder1	IBinder
    //   34	16	7	localIBinder2	IBinder
    // Exception table:
    //   from	to	target	type
    //   9	15	91	finally
    //   19	27	91	finally
    //   27	33	91	finally
    //   40	48	91	finally
    //   48	75	91	finally
  }
  
  /* Error */
  public void a(ILocationSourceDelegate paramILocationSourceDelegate)
  {
    // Byte code:
    //   0: invokestatic 22	android/os/Parcel:obtain	()Landroid/os/Parcel;
    //   3: astore_2
    //   4: invokestatic 22	android/os/Parcel:obtain	()Landroid/os/Parcel;
    //   7: astore_3
    //   8: aload_2
    //   9: ldc 24
    //   11: invokevirtual 28	android/os/Parcel:writeInterfaceToken	(Ljava/lang/String;)V
    //   14: aload_1
    //   15: ifnull +45 -> 60
    //   18: aload_1
    //   19: invokeinterface 151 1 0
    //   24: astore 5
    //   26: aload_2
    //   27: aload 5
    //   29: invokevirtual 142	android/os/Parcel:writeStrongBinder	(Landroid/os/IBinder;)V
    //   32: aload_0
    //   33: getfield 15	com/google/android/gms/maps/internal/IGoogleMapDelegate$a$a:a	Landroid/os/IBinder;
    //   36: bipush 24
    //   38: aload_2
    //   39: aload_3
    //   40: iconst_0
    //   41: invokeinterface 34 5 0
    //   46: pop
    //   47: aload_3
    //   48: invokevirtual 37	android/os/Parcel:readException	()V
    //   51: aload_3
    //   52: invokevirtual 55	android/os/Parcel:recycle	()V
    //   55: aload_2
    //   56: invokevirtual 55	android/os/Parcel:recycle	()V
    //   59: return
    //   60: aconst_null
    //   61: astore 5
    //   63: goto -37 -> 26
    //   66: astore 4
    //   68: aload_3
    //   69: invokevirtual 55	android/os/Parcel:recycle	()V
    //   72: aload_2
    //   73: invokevirtual 55	android/os/Parcel:recycle	()V
    //   76: aload 4
    //   78: athrow
    // Local variable table:
    //   start	length	slot	name	signature
    //   0	79	0	this	a
    //   0	79	1	paramILocationSourceDelegate	ILocationSourceDelegate
    //   3	70	2	localParcel1	Parcel
    //   7	62	3	localParcel2	Parcel
    //   66	11	4	localObject	Object
    //   24	38	5	localIBinder	IBinder
    // Exception table:
    //   from	to	target	type
    //   8	14	66	finally
    //   18	26	66	finally
    //   26	51	66	finally
  }
  
  /* Error */
  public void a(d paramd)
  {
    // Byte code:
    //   0: invokestatic 22	android/os/Parcel:obtain	()Landroid/os/Parcel;
    //   3: astore_2
    //   4: invokestatic 22	android/os/Parcel:obtain	()Landroid/os/Parcel;
    //   7: astore_3
    //   8: aload_2
    //   9: ldc 24
    //   11: invokevirtual 28	android/os/Parcel:writeInterfaceToken	(Ljava/lang/String;)V
    //   14: aload_1
    //   15: ifnull +45 -> 60
    //   18: aload_1
    //   19: invokeinterface 155 1 0
    //   24: astore 5
    //   26: aload_2
    //   27: aload 5
    //   29: invokevirtual 142	android/os/Parcel:writeStrongBinder	(Landroid/os/IBinder;)V
    //   32: aload_0
    //   33: getfield 15	com/google/android/gms/maps/internal/IGoogleMapDelegate$a$a:a	Landroid/os/IBinder;
    //   36: bipush 33
    //   38: aload_2
    //   39: aload_3
    //   40: iconst_0
    //   41: invokeinterface 34 5 0
    //   46: pop
    //   47: aload_3
    //   48: invokevirtual 37	android/os/Parcel:readException	()V
    //   51: aload_3
    //   52: invokevirtual 55	android/os/Parcel:recycle	()V
    //   55: aload_2
    //   56: invokevirtual 55	android/os/Parcel:recycle	()V
    //   59: return
    //   60: aconst_null
    //   61: astore 5
    //   63: goto -37 -> 26
    //   66: astore 4
    //   68: aload_3
    //   69: invokevirtual 55	android/os/Parcel:recycle	()V
    //   72: aload_2
    //   73: invokevirtual 55	android/os/Parcel:recycle	()V
    //   76: aload 4
    //   78: athrow
    // Local variable table:
    //   start	length	slot	name	signature
    //   0	79	0	this	a
    //   0	79	1	paramd	d
    //   3	70	2	localParcel1	Parcel
    //   7	62	3	localParcel2	Parcel
    //   66	11	4	localObject	Object
    //   24	38	5	localIBinder	IBinder
    // Exception table:
    //   from	to	target	type
    //   8	14	66	finally
    //   18	26	66	finally
    //   26	51	66	finally
  }
  
  /* Error */
  public void a(e parame)
  {
    // Byte code:
    //   0: invokestatic 22	android/os/Parcel:obtain	()Landroid/os/Parcel;
    //   3: astore_2
    //   4: invokestatic 22	android/os/Parcel:obtain	()Landroid/os/Parcel;
    //   7: astore_3
    //   8: aload_2
    //   9: ldc 24
    //   11: invokevirtual 28	android/os/Parcel:writeInterfaceToken	(Ljava/lang/String;)V
    //   14: aload_1
    //   15: ifnull +45 -> 60
    //   18: aload_1
    //   19: invokeinterface 159 1 0
    //   24: astore 5
    //   26: aload_2
    //   27: aload 5
    //   29: invokevirtual 142	android/os/Parcel:writeStrongBinder	(Landroid/os/IBinder;)V
    //   32: aload_0
    //   33: getfield 15	com/google/android/gms/maps/internal/IGoogleMapDelegate$a$a:a	Landroid/os/IBinder;
    //   36: bipush 69
    //   38: aload_2
    //   39: aload_3
    //   40: iconst_0
    //   41: invokeinterface 34 5 0
    //   46: pop
    //   47: aload_3
    //   48: invokevirtual 37	android/os/Parcel:readException	()V
    //   51: aload_3
    //   52: invokevirtual 55	android/os/Parcel:recycle	()V
    //   55: aload_2
    //   56: invokevirtual 55	android/os/Parcel:recycle	()V
    //   59: return
    //   60: aconst_null
    //   61: astore 5
    //   63: goto -37 -> 26
    //   66: astore 4
    //   68: aload_3
    //   69: invokevirtual 55	android/os/Parcel:recycle	()V
    //   72: aload_2
    //   73: invokevirtual 55	android/os/Parcel:recycle	()V
    //   76: aload 4
    //   78: athrow
    // Local variable table:
    //   start	length	slot	name	signature
    //   0	79	0	this	a
    //   0	79	1	parame	e
    //   3	70	2	localParcel1	Parcel
    //   7	62	3	localParcel2	Parcel
    //   66	11	4	localObject	Object
    //   24	38	5	localIBinder	IBinder
    // Exception table:
    //   from	to	target	type
    //   8	14	66	finally
    //   18	26	66	finally
    //   26	51	66	finally
  }
  
  /* Error */
  public void a(f paramf)
  {
    // Byte code:
    //   0: invokestatic 22	android/os/Parcel:obtain	()Landroid/os/Parcel;
    //   3: astore_2
    //   4: invokestatic 22	android/os/Parcel:obtain	()Landroid/os/Parcel;
    //   7: astore_3
    //   8: aload_2
    //   9: ldc 24
    //   11: invokevirtual 28	android/os/Parcel:writeInterfaceToken	(Ljava/lang/String;)V
    //   14: aload_1
    //   15: ifnull +45 -> 60
    //   18: aload_1
    //   19: invokeinterface 163 1 0
    //   24: astore 5
    //   26: aload_2
    //   27: aload 5
    //   29: invokevirtual 142	android/os/Parcel:writeStrongBinder	(Landroid/os/IBinder;)V
    //   32: aload_0
    //   33: getfield 15	com/google/android/gms/maps/internal/IGoogleMapDelegate$a$a:a	Landroid/os/IBinder;
    //   36: bipush 27
    //   38: aload_2
    //   39: aload_3
    //   40: iconst_0
    //   41: invokeinterface 34 5 0
    //   46: pop
    //   47: aload_3
    //   48: invokevirtual 37	android/os/Parcel:readException	()V
    //   51: aload_3
    //   52: invokevirtual 55	android/os/Parcel:recycle	()V
    //   55: aload_2
    //   56: invokevirtual 55	android/os/Parcel:recycle	()V
    //   59: return
    //   60: aconst_null
    //   61: astore 5
    //   63: goto -37 -> 26
    //   66: astore 4
    //   68: aload_3
    //   69: invokevirtual 55	android/os/Parcel:recycle	()V
    //   72: aload_2
    //   73: invokevirtual 55	android/os/Parcel:recycle	()V
    //   76: aload 4
    //   78: athrow
    // Local variable table:
    //   start	length	slot	name	signature
    //   0	79	0	this	a
    //   0	79	1	paramf	f
    //   3	70	2	localParcel1	Parcel
    //   7	62	3	localParcel2	Parcel
    //   66	11	4	localObject	Object
    //   24	38	5	localIBinder	IBinder
    // Exception table:
    //   from	to	target	type
    //   8	14	66	finally
    //   18	26	66	finally
    //   26	51	66	finally
  }
  
  /* Error */
  public void a(g paramg)
  {
    // Byte code:
    //   0: invokestatic 22	android/os/Parcel:obtain	()Landroid/os/Parcel;
    //   3: astore_2
    //   4: invokestatic 22	android/os/Parcel:obtain	()Landroid/os/Parcel;
    //   7: astore_3
    //   8: aload_2
    //   9: ldc 24
    //   11: invokevirtual 28	android/os/Parcel:writeInterfaceToken	(Ljava/lang/String;)V
    //   14: aload_1
    //   15: ifnull +45 -> 60
    //   18: aload_1
    //   19: invokeinterface 167 1 0
    //   24: astore 5
    //   26: aload_2
    //   27: aload 5
    //   29: invokevirtual 142	android/os/Parcel:writeStrongBinder	(Landroid/os/IBinder;)V
    //   32: aload_0
    //   33: getfield 15	com/google/android/gms/maps/internal/IGoogleMapDelegate$a$a:a	Landroid/os/IBinder;
    //   36: bipush 45
    //   38: aload_2
    //   39: aload_3
    //   40: iconst_0
    //   41: invokeinterface 34 5 0
    //   46: pop
    //   47: aload_3
    //   48: invokevirtual 37	android/os/Parcel:readException	()V
    //   51: aload_3
    //   52: invokevirtual 55	android/os/Parcel:recycle	()V
    //   55: aload_2
    //   56: invokevirtual 55	android/os/Parcel:recycle	()V
    //   59: return
    //   60: aconst_null
    //   61: astore 5
    //   63: goto -37 -> 26
    //   66: astore 4
    //   68: aload_3
    //   69: invokevirtual 55	android/os/Parcel:recycle	()V
    //   72: aload_2
    //   73: invokevirtual 55	android/os/Parcel:recycle	()V
    //   76: aload 4
    //   78: athrow
    // Local variable table:
    //   start	length	slot	name	signature
    //   0	79	0	this	a
    //   0	79	1	paramg	g
    //   3	70	2	localParcel1	Parcel
    //   7	62	3	localParcel2	Parcel
    //   66	11	4	localObject	Object
    //   24	38	5	localIBinder	IBinder
    // Exception table:
    //   from	to	target	type
    //   8	14	66	finally
    //   18	26	66	finally
    //   26	51	66	finally
  }
  
  /* Error */
  public void a(h paramh)
  {
    // Byte code:
    //   0: invokestatic 22	android/os/Parcel:obtain	()Landroid/os/Parcel;
    //   3: astore_2
    //   4: invokestatic 22	android/os/Parcel:obtain	()Landroid/os/Parcel;
    //   7: astore_3
    //   8: aload_2
    //   9: ldc 24
    //   11: invokevirtual 28	android/os/Parcel:writeInterfaceToken	(Ljava/lang/String;)V
    //   14: aload_1
    //   15: ifnull +45 -> 60
    //   18: aload_1
    //   19: invokeinterface 171 1 0
    //   24: astore 5
    //   26: aload_2
    //   27: aload 5
    //   29: invokevirtual 142	android/os/Parcel:writeStrongBinder	(Landroid/os/IBinder;)V
    //   32: aload_0
    //   33: getfield 15	com/google/android/gms/maps/internal/IGoogleMapDelegate$a$a:a	Landroid/os/IBinder;
    //   36: bipush 32
    //   38: aload_2
    //   39: aload_3
    //   40: iconst_0
    //   41: invokeinterface 34 5 0
    //   46: pop
    //   47: aload_3
    //   48: invokevirtual 37	android/os/Parcel:readException	()V
    //   51: aload_3
    //   52: invokevirtual 55	android/os/Parcel:recycle	()V
    //   55: aload_2
    //   56: invokevirtual 55	android/os/Parcel:recycle	()V
    //   59: return
    //   60: aconst_null
    //   61: astore 5
    //   63: goto -37 -> 26
    //   66: astore 4
    //   68: aload_3
    //   69: invokevirtual 55	android/os/Parcel:recycle	()V
    //   72: aload_2
    //   73: invokevirtual 55	android/os/Parcel:recycle	()V
    //   76: aload 4
    //   78: athrow
    // Local variable table:
    //   start	length	slot	name	signature
    //   0	79	0	this	a
    //   0	79	1	paramh	h
    //   3	70	2	localParcel1	Parcel
    //   7	62	3	localParcel2	Parcel
    //   66	11	4	localObject	Object
    //   24	38	5	localIBinder	IBinder
    // Exception table:
    //   from	to	target	type
    //   8	14	66	finally
    //   18	26	66	finally
    //   26	51	66	finally
  }
  
  /* Error */
  public void a(j paramj)
  {
    // Byte code:
    //   0: invokestatic 22	android/os/Parcel:obtain	()Landroid/os/Parcel;
    //   3: astore_2
    //   4: invokestatic 22	android/os/Parcel:obtain	()Landroid/os/Parcel;
    //   7: astore_3
    //   8: aload_2
    //   9: ldc 24
    //   11: invokevirtual 28	android/os/Parcel:writeInterfaceToken	(Ljava/lang/String;)V
    //   14: aload_1
    //   15: ifnull +45 -> 60
    //   18: aload_1
    //   19: invokeinterface 175 1 0
    //   24: astore 5
    //   26: aload_2
    //   27: aload 5
    //   29: invokevirtual 142	android/os/Parcel:writeStrongBinder	(Landroid/os/IBinder;)V
    //   32: aload_0
    //   33: getfield 15	com/google/android/gms/maps/internal/IGoogleMapDelegate$a$a:a	Landroid/os/IBinder;
    //   36: bipush 28
    //   38: aload_2
    //   39: aload_3
    //   40: iconst_0
    //   41: invokeinterface 34 5 0
    //   46: pop
    //   47: aload_3
    //   48: invokevirtual 37	android/os/Parcel:readException	()V
    //   51: aload_3
    //   52: invokevirtual 55	android/os/Parcel:recycle	()V
    //   55: aload_2
    //   56: invokevirtual 55	android/os/Parcel:recycle	()V
    //   59: return
    //   60: aconst_null
    //   61: astore 5
    //   63: goto -37 -> 26
    //   66: astore 4
    //   68: aload_3
    //   69: invokevirtual 55	android/os/Parcel:recycle	()V
    //   72: aload_2
    //   73: invokevirtual 55	android/os/Parcel:recycle	()V
    //   76: aload 4
    //   78: athrow
    // Local variable table:
    //   start	length	slot	name	signature
    //   0	79	0	this	a
    //   0	79	1	paramj	j
    //   3	70	2	localParcel1	Parcel
    //   7	62	3	localParcel2	Parcel
    //   66	11	4	localObject	Object
    //   24	38	5	localIBinder	IBinder
    // Exception table:
    //   from	to	target	type
    //   8	14	66	finally
    //   18	26	66	finally
    //   26	51	66	finally
  }
  
  /* Error */
  public void a(k paramk)
  {
    // Byte code:
    //   0: invokestatic 22	android/os/Parcel:obtain	()Landroid/os/Parcel;
    //   3: astore_2
    //   4: invokestatic 22	android/os/Parcel:obtain	()Landroid/os/Parcel;
    //   7: astore_3
    //   8: aload_2
    //   9: ldc 24
    //   11: invokevirtual 28	android/os/Parcel:writeInterfaceToken	(Ljava/lang/String;)V
    //   14: aload_1
    //   15: ifnull +45 -> 60
    //   18: aload_1
    //   19: invokeinterface 179 1 0
    //   24: astore 5
    //   26: aload_2
    //   27: aload 5
    //   29: invokevirtual 142	android/os/Parcel:writeStrongBinder	(Landroid/os/IBinder;)V
    //   32: aload_0
    //   33: getfield 15	com/google/android/gms/maps/internal/IGoogleMapDelegate$a$a:a	Landroid/os/IBinder;
    //   36: bipush 42
    //   38: aload_2
    //   39: aload_3
    //   40: iconst_0
    //   41: invokeinterface 34 5 0
    //   46: pop
    //   47: aload_3
    //   48: invokevirtual 37	android/os/Parcel:readException	()V
    //   51: aload_3
    //   52: invokevirtual 55	android/os/Parcel:recycle	()V
    //   55: aload_2
    //   56: invokevirtual 55	android/os/Parcel:recycle	()V
    //   59: return
    //   60: aconst_null
    //   61: astore 5
    //   63: goto -37 -> 26
    //   66: astore 4
    //   68: aload_3
    //   69: invokevirtual 55	android/os/Parcel:recycle	()V
    //   72: aload_2
    //   73: invokevirtual 55	android/os/Parcel:recycle	()V
    //   76: aload 4
    //   78: athrow
    // Local variable table:
    //   start	length	slot	name	signature
    //   0	79	0	this	a
    //   0	79	1	paramk	k
    //   3	70	2	localParcel1	Parcel
    //   7	62	3	localParcel2	Parcel
    //   66	11	4	localObject	Object
    //   24	38	5	localIBinder	IBinder
    // Exception table:
    //   from	to	target	type
    //   8	14	66	finally
    //   18	26	66	finally
    //   26	51	66	finally
  }
  
  /* Error */
  public void a(l paraml)
  {
    // Byte code:
    //   0: invokestatic 22	android/os/Parcel:obtain	()Landroid/os/Parcel;
    //   3: astore_2
    //   4: invokestatic 22	android/os/Parcel:obtain	()Landroid/os/Parcel;
    //   7: astore_3
    //   8: aload_2
    //   9: ldc 24
    //   11: invokevirtual 28	android/os/Parcel:writeInterfaceToken	(Ljava/lang/String;)V
    //   14: aload_1
    //   15: ifnull +45 -> 60
    //   18: aload_1
    //   19: invokeinterface 183 1 0
    //   24: astore 5
    //   26: aload_2
    //   27: aload 5
    //   29: invokevirtual 142	android/os/Parcel:writeStrongBinder	(Landroid/os/IBinder;)V
    //   32: aload_0
    //   33: getfield 15	com/google/android/gms/maps/internal/IGoogleMapDelegate$a$a:a	Landroid/os/IBinder;
    //   36: bipush 29
    //   38: aload_2
    //   39: aload_3
    //   40: iconst_0
    //   41: invokeinterface 34 5 0
    //   46: pop
    //   47: aload_3
    //   48: invokevirtual 37	android/os/Parcel:readException	()V
    //   51: aload_3
    //   52: invokevirtual 55	android/os/Parcel:recycle	()V
    //   55: aload_2
    //   56: invokevirtual 55	android/os/Parcel:recycle	()V
    //   59: return
    //   60: aconst_null
    //   61: astore 5
    //   63: goto -37 -> 26
    //   66: astore 4
    //   68: aload_3
    //   69: invokevirtual 55	android/os/Parcel:recycle	()V
    //   72: aload_2
    //   73: invokevirtual 55	android/os/Parcel:recycle	()V
    //   76: aload 4
    //   78: athrow
    // Local variable table:
    //   start	length	slot	name	signature
    //   0	79	0	this	a
    //   0	79	1	paraml	l
    //   3	70	2	localParcel1	Parcel
    //   7	62	3	localParcel2	Parcel
    //   66	11	4	localObject	Object
    //   24	38	5	localIBinder	IBinder
    // Exception table:
    //   from	to	target	type
    //   8	14	66	finally
    //   18	26	66	finally
    //   26	51	66	finally
  }
  
  /* Error */
  public void a(m paramm)
  {
    // Byte code:
    //   0: invokestatic 22	android/os/Parcel:obtain	()Landroid/os/Parcel;
    //   3: astore_2
    //   4: invokestatic 22	android/os/Parcel:obtain	()Landroid/os/Parcel;
    //   7: astore_3
    //   8: aload_2
    //   9: ldc 24
    //   11: invokevirtual 28	android/os/Parcel:writeInterfaceToken	(Ljava/lang/String;)V
    //   14: aload_1
    //   15: ifnull +45 -> 60
    //   18: aload_1
    //   19: invokeinterface 187 1 0
    //   24: astore 5
    //   26: aload_2
    //   27: aload 5
    //   29: invokevirtual 142	android/os/Parcel:writeStrongBinder	(Landroid/os/IBinder;)V
    //   32: aload_0
    //   33: getfield 15	com/google/android/gms/maps/internal/IGoogleMapDelegate$a$a:a	Landroid/os/IBinder;
    //   36: bipush 53
    //   38: aload_2
    //   39: aload_3
    //   40: iconst_0
    //   41: invokeinterface 34 5 0
    //   46: pop
    //   47: aload_3
    //   48: invokevirtual 37	android/os/Parcel:readException	()V
    //   51: aload_3
    //   52: invokevirtual 55	android/os/Parcel:recycle	()V
    //   55: aload_2
    //   56: invokevirtual 55	android/os/Parcel:recycle	()V
    //   59: return
    //   60: aconst_null
    //   61: astore 5
    //   63: goto -37 -> 26
    //   66: astore 4
    //   68: aload_3
    //   69: invokevirtual 55	android/os/Parcel:recycle	()V
    //   72: aload_2
    //   73: invokevirtual 55	android/os/Parcel:recycle	()V
    //   76: aload 4
    //   78: athrow
    // Local variable table:
    //   start	length	slot	name	signature
    //   0	79	0	this	a
    //   0	79	1	paramm	m
    //   3	70	2	localParcel1	Parcel
    //   7	62	3	localParcel2	Parcel
    //   66	11	4	localObject	Object
    //   24	38	5	localIBinder	IBinder
    // Exception table:
    //   from	to	target	type
    //   8	14	66	finally
    //   18	26	66	finally
    //   26	51	66	finally
  }
  
  /* Error */
  public void a(n paramn)
  {
    // Byte code:
    //   0: invokestatic 22	android/os/Parcel:obtain	()Landroid/os/Parcel;
    //   3: astore_2
    //   4: invokestatic 22	android/os/Parcel:obtain	()Landroid/os/Parcel;
    //   7: astore_3
    //   8: aload_2
    //   9: ldc 24
    //   11: invokevirtual 28	android/os/Parcel:writeInterfaceToken	(Ljava/lang/String;)V
    //   14: aload_1
    //   15: ifnull +45 -> 60
    //   18: aload_1
    //   19: invokeinterface 191 1 0
    //   24: astore 5
    //   26: aload_2
    //   27: aload 5
    //   29: invokevirtual 142	android/os/Parcel:writeStrongBinder	(Landroid/os/IBinder;)V
    //   32: aload_0
    //   33: getfield 15	com/google/android/gms/maps/internal/IGoogleMapDelegate$a$a:a	Landroid/os/IBinder;
    //   36: bipush 30
    //   38: aload_2
    //   39: aload_3
    //   40: iconst_0
    //   41: invokeinterface 34 5 0
    //   46: pop
    //   47: aload_3
    //   48: invokevirtual 37	android/os/Parcel:readException	()V
    //   51: aload_3
    //   52: invokevirtual 55	android/os/Parcel:recycle	()V
    //   55: aload_2
    //   56: invokevirtual 55	android/os/Parcel:recycle	()V
    //   59: return
    //   60: aconst_null
    //   61: astore 5
    //   63: goto -37 -> 26
    //   66: astore 4
    //   68: aload_3
    //   69: invokevirtual 55	android/os/Parcel:recycle	()V
    //   72: aload_2
    //   73: invokevirtual 55	android/os/Parcel:recycle	()V
    //   76: aload 4
    //   78: athrow
    // Local variable table:
    //   start	length	slot	name	signature
    //   0	79	0	this	a
    //   0	79	1	paramn	n
    //   3	70	2	localParcel1	Parcel
    //   7	62	3	localParcel2	Parcel
    //   66	11	4	localObject	Object
    //   24	38	5	localIBinder	IBinder
    // Exception table:
    //   from	to	target	type
    //   8	14	66	finally
    //   18	26	66	finally
    //   26	51	66	finally
  }
  
  /* Error */
  public void a(o paramo)
  {
    // Byte code:
    //   0: invokestatic 22	android/os/Parcel:obtain	()Landroid/os/Parcel;
    //   3: astore_2
    //   4: invokestatic 22	android/os/Parcel:obtain	()Landroid/os/Parcel;
    //   7: astore_3
    //   8: aload_2
    //   9: ldc 24
    //   11: invokevirtual 28	android/os/Parcel:writeInterfaceToken	(Ljava/lang/String;)V
    //   14: aload_1
    //   15: ifnull +45 -> 60
    //   18: aload_1
    //   19: invokeinterface 195 1 0
    //   24: astore 5
    //   26: aload_2
    //   27: aload 5
    //   29: invokevirtual 142	android/os/Parcel:writeStrongBinder	(Landroid/os/IBinder;)V
    //   32: aload_0
    //   33: getfield 15	com/google/android/gms/maps/internal/IGoogleMapDelegate$a$a:a	Landroid/os/IBinder;
    //   36: bipush 31
    //   38: aload_2
    //   39: aload_3
    //   40: iconst_0
    //   41: invokeinterface 34 5 0
    //   46: pop
    //   47: aload_3
    //   48: invokevirtual 37	android/os/Parcel:readException	()V
    //   51: aload_3
    //   52: invokevirtual 55	android/os/Parcel:recycle	()V
    //   55: aload_2
    //   56: invokevirtual 55	android/os/Parcel:recycle	()V
    //   59: return
    //   60: aconst_null
    //   61: astore 5
    //   63: goto -37 -> 26
    //   66: astore 4
    //   68: aload_3
    //   69: invokevirtual 55	android/os/Parcel:recycle	()V
    //   72: aload_2
    //   73: invokevirtual 55	android/os/Parcel:recycle	()V
    //   76: aload 4
    //   78: athrow
    // Local variable table:
    //   start	length	slot	name	signature
    //   0	79	0	this	a
    //   0	79	1	paramo	o
    //   3	70	2	localParcel1	Parcel
    //   7	62	3	localParcel2	Parcel
    //   66	11	4	localObject	Object
    //   24	38	5	localIBinder	IBinder
    // Exception table:
    //   from	to	target	type
    //   8	14	66	finally
    //   18	26	66	finally
    //   26	51	66	finally
  }
  
  /* Error */
  public void a(p paramp)
  {
    // Byte code:
    //   0: invokestatic 22	android/os/Parcel:obtain	()Landroid/os/Parcel;
    //   3: astore_2
    //   4: invokestatic 22	android/os/Parcel:obtain	()Landroid/os/Parcel;
    //   7: astore_3
    //   8: aload_2
    //   9: ldc 24
    //   11: invokevirtual 28	android/os/Parcel:writeInterfaceToken	(Ljava/lang/String;)V
    //   14: aload_1
    //   15: ifnull +45 -> 60
    //   18: aload_1
    //   19: invokeinterface 199 1 0
    //   24: astore 5
    //   26: aload_2
    //   27: aload 5
    //   29: invokevirtual 142	android/os/Parcel:writeStrongBinder	(Landroid/os/IBinder;)V
    //   32: aload_0
    //   33: getfield 15	com/google/android/gms/maps/internal/IGoogleMapDelegate$a$a:a	Landroid/os/IBinder;
    //   36: bipush 37
    //   38: aload_2
    //   39: aload_3
    //   40: iconst_0
    //   41: invokeinterface 34 5 0
    //   46: pop
    //   47: aload_3
    //   48: invokevirtual 37	android/os/Parcel:readException	()V
    //   51: aload_3
    //   52: invokevirtual 55	android/os/Parcel:recycle	()V
    //   55: aload_2
    //   56: invokevirtual 55	android/os/Parcel:recycle	()V
    //   59: return
    //   60: aconst_null
    //   61: astore 5
    //   63: goto -37 -> 26
    //   66: astore 4
    //   68: aload_3
    //   69: invokevirtual 55	android/os/Parcel:recycle	()V
    //   72: aload_2
    //   73: invokevirtual 55	android/os/Parcel:recycle	()V
    //   76: aload 4
    //   78: athrow
    // Local variable table:
    //   start	length	slot	name	signature
    //   0	79	0	this	a
    //   0	79	1	paramp	p
    //   3	70	2	localParcel1	Parcel
    //   7	62	3	localParcel2	Parcel
    //   66	11	4	localObject	Object
    //   24	38	5	localIBinder	IBinder
    // Exception table:
    //   from	to	target	type
    //   8	14	66	finally
    //   18	26	66	finally
    //   26	51	66	finally
  }
  
  /* Error */
  public void a(q paramq)
  {
    // Byte code:
    //   0: invokestatic 22	android/os/Parcel:obtain	()Landroid/os/Parcel;
    //   3: astore_2
    //   4: invokestatic 22	android/os/Parcel:obtain	()Landroid/os/Parcel;
    //   7: astore_3
    //   8: aload_2
    //   9: ldc 24
    //   11: invokevirtual 28	android/os/Parcel:writeInterfaceToken	(Ljava/lang/String;)V
    //   14: aload_1
    //   15: ifnull +45 -> 60
    //   18: aload_1
    //   19: invokeinterface 203 1 0
    //   24: astore 5
    //   26: aload_2
    //   27: aload 5
    //   29: invokevirtual 142	android/os/Parcel:writeStrongBinder	(Landroid/os/IBinder;)V
    //   32: aload_0
    //   33: getfield 15	com/google/android/gms/maps/internal/IGoogleMapDelegate$a$a:a	Landroid/os/IBinder;
    //   36: bipush 36
    //   38: aload_2
    //   39: aload_3
    //   40: iconst_0
    //   41: invokeinterface 34 5 0
    //   46: pop
    //   47: aload_3
    //   48: invokevirtual 37	android/os/Parcel:readException	()V
    //   51: aload_3
    //   52: invokevirtual 55	android/os/Parcel:recycle	()V
    //   55: aload_2
    //   56: invokevirtual 55	android/os/Parcel:recycle	()V
    //   59: return
    //   60: aconst_null
    //   61: astore 5
    //   63: goto -37 -> 26
    //   66: astore 4
    //   68: aload_3
    //   69: invokevirtual 55	android/os/Parcel:recycle	()V
    //   72: aload_2
    //   73: invokevirtual 55	android/os/Parcel:recycle	()V
    //   76: aload 4
    //   78: athrow
    // Local variable table:
    //   start	length	slot	name	signature
    //   0	79	0	this	a
    //   0	79	1	paramq	q
    //   3	70	2	localParcel1	Parcel
    //   7	62	3	localParcel2	Parcel
    //   66	11	4	localObject	Object
    //   24	38	5	localIBinder	IBinder
    // Exception table:
    //   from	to	target	type
    //   8	14	66	finally
    //   18	26	66	finally
    //   26	51	66	finally
  }
  
  /* Error */
  public void a(v paramv, com.google.android.gms.dynamic.d paramd)
  {
    // Byte code:
    //   0: invokestatic 22	android/os/Parcel:obtain	()Landroid/os/Parcel;
    //   3: astore_3
    //   4: invokestatic 22	android/os/Parcel:obtain	()Landroid/os/Parcel;
    //   7: astore 4
    //   9: aload_3
    //   10: ldc 24
    //   12: invokevirtual 28	android/os/Parcel:writeInterfaceToken	(Ljava/lang/String;)V
    //   15: aload_1
    //   16: ifnull +69 -> 85
    //   19: aload_1
    //   20: invokeinterface 207 1 0
    //   25: astore 6
    //   27: aload_3
    //   28: aload 6
    //   30: invokevirtual 142	android/os/Parcel:writeStrongBinder	(Landroid/os/IBinder;)V
    //   33: aconst_null
    //   34: astore 7
    //   36: aload_2
    //   37: ifnull +11 -> 48
    //   40: aload_2
    //   41: invokeinterface 139 1 0
    //   46: astore 7
    //   48: aload_3
    //   49: aload 7
    //   51: invokevirtual 142	android/os/Parcel:writeStrongBinder	(Landroid/os/IBinder;)V
    //   54: aload_0
    //   55: getfield 15	com/google/android/gms/maps/internal/IGoogleMapDelegate$a$a:a	Landroid/os/IBinder;
    //   58: bipush 38
    //   60: aload_3
    //   61: aload 4
    //   63: iconst_0
    //   64: invokeinterface 34 5 0
    //   69: pop
    //   70: aload 4
    //   72: invokevirtual 37	android/os/Parcel:readException	()V
    //   75: aload 4
    //   77: invokevirtual 55	android/os/Parcel:recycle	()V
    //   80: aload_3
    //   81: invokevirtual 55	android/os/Parcel:recycle	()V
    //   84: return
    //   85: aconst_null
    //   86: astore 6
    //   88: goto -61 -> 27
    //   91: astore 5
    //   93: aload 4
    //   95: invokevirtual 55	android/os/Parcel:recycle	()V
    //   98: aload_3
    //   99: invokevirtual 55	android/os/Parcel:recycle	()V
    //   102: aload 5
    //   104: athrow
    // Local variable table:
    //   start	length	slot	name	signature
    //   0	105	0	this	a
    //   0	105	1	paramv	v
    //   0	105	2	paramd	com.google.android.gms.dynamic.d
    //   3	96	3	localParcel1	Parcel
    //   7	87	4	localParcel2	Parcel
    //   91	12	5	localObject	Object
    //   25	62	6	localIBinder1	IBinder
    //   34	16	7	localIBinder2	IBinder
    // Exception table:
    //   from	to	target	type
    //   9	15	91	finally
    //   19	27	91	finally
    //   27	33	91	finally
    //   40	48	91	finally
    //   48	75	91	finally
  }
  
  /* Error */
  public void a(c paramc)
  {
    // Byte code:
    //   0: invokestatic 22	android/os/Parcel:obtain	()Landroid/os/Parcel;
    //   3: astore_2
    //   4: invokestatic 22	android/os/Parcel:obtain	()Landroid/os/Parcel;
    //   7: astore_3
    //   8: aload_2
    //   9: ldc 24
    //   11: invokevirtual 28	android/os/Parcel:writeInterfaceToken	(Ljava/lang/String;)V
    //   14: aload_1
    //   15: ifnull +42 -> 57
    //   18: aload_2
    //   19: iconst_1
    //   20: invokevirtual 60	android/os/Parcel:writeInt	(I)V
    //   23: aload_1
    //   24: aload_2
    //   25: iconst_0
    //   26: invokevirtual 211	com/google/android/gms/maps/model/internal/c:writeToParcel	(Landroid/os/Parcel;I)V
    //   29: aload_0
    //   30: getfield 15	com/google/android/gms/maps/internal/IGoogleMapDelegate$a$a:a	Landroid/os/IBinder;
    //   33: bipush 64
    //   35: aload_2
    //   36: aload_3
    //   37: iconst_0
    //   38: invokeinterface 34 5 0
    //   43: pop
    //   44: aload_3
    //   45: invokevirtual 37	android/os/Parcel:readException	()V
    //   48: aload_3
    //   49: invokevirtual 55	android/os/Parcel:recycle	()V
    //   52: aload_2
    //   53: invokevirtual 55	android/os/Parcel:recycle	()V
    //   56: return
    //   57: aload_2
    //   58: iconst_0
    //   59: invokevirtual 60	android/os/Parcel:writeInt	(I)V
    //   62: goto -33 -> 29
    //   65: astore 4
    //   67: aload_3
    //   68: invokevirtual 55	android/os/Parcel:recycle	()V
    //   71: aload_2
    //   72: invokevirtual 55	android/os/Parcel:recycle	()V
    //   75: aload 4
    //   77: athrow
    // Local variable table:
    //   start	length	slot	name	signature
    //   0	78	0	this	a
    //   0	78	1	paramc	c
    //   3	69	2	localParcel1	Parcel
    //   7	61	3	localParcel2	Parcel
    //   65	11	4	localObject	Object
    // Exception table:
    //   from	to	target	type
    //   8	14	65	finally
    //   18	29	65	finally
    //   29	48	65	finally
    //   57	62	65	finally
  }
  
  public void a(c paramc, int paramInt, b paramb)
  {
    Parcel localParcel1 = Parcel.obtain();
    Parcel localParcel2 = Parcel.obtain();
    for (;;)
    {
      try
      {
        localParcel1.writeInterfaceToken("com.google.android.gms.maps.internal.IGoogleMapDelegate");
        if (paramc != null)
        {
          localParcel1.writeInt(1);
          paramc.writeToParcel(localParcel1, 0);
          localParcel1.writeInt(paramInt);
          if (paramb != null)
          {
            localIBinder = paramb.asBinder();
            localParcel1.writeStrongBinder(localIBinder);
            this.a.transact(67, localParcel1, localParcel2, 0);
            localParcel2.readException();
          }
        }
        else
        {
          localParcel1.writeInt(0);
          continue;
        }
        IBinder localIBinder = null;
      }
      finally
      {
        localParcel2.recycle();
        localParcel1.recycle();
      }
    }
  }
  
  public void a(c paramc, b paramb)
  {
    Parcel localParcel1 = Parcel.obtain();
    Parcel localParcel2 = Parcel.obtain();
    for (;;)
    {
      try
      {
        localParcel1.writeInterfaceToken("com.google.android.gms.maps.internal.IGoogleMapDelegate");
        if (paramc != null)
        {
          localParcel1.writeInt(1);
          paramc.writeToParcel(localParcel1, 0);
          if (paramb != null)
          {
            localIBinder = paramb.asBinder();
            localParcel1.writeStrongBinder(localIBinder);
            this.a.transact(66, localParcel1, localParcel2, 0);
            localParcel2.readException();
          }
        }
        else
        {
          localParcel1.writeInt(0);
          continue;
        }
        IBinder localIBinder = null;
      }
      finally
      {
        localParcel2.recycle();
        localParcel1.recycle();
      }
    }
  }
  
  public void a(String paramString)
  {
    Parcel localParcel1 = Parcel.obtain();
    Parcel localParcel2 = Parcel.obtain();
    try
    {
      localParcel1.writeInterfaceToken("com.google.android.gms.maps.internal.IGoogleMapDelegate");
      localParcel1.writeString(paramString);
      this.a.transact(61, localParcel1, localParcel2, 0);
      localParcel2.readException();
      return;
    }
    finally
    {
      localParcel2.recycle();
      localParcel1.recycle();
    }
  }
  
  public void a(boolean paramBoolean)
  {
    Parcel localParcel1 = Parcel.obtain();
    Parcel localParcel2 = Parcel.obtain();
    try
    {
      localParcel1.writeInterfaceToken("com.google.android.gms.maps.internal.IGoogleMapDelegate");
      int i = 0;
      if (paramBoolean) {
        i = 1;
      }
      localParcel1.writeInt(i);
      this.a.transact(18, localParcel1, localParcel2, 0);
      localParcel2.readException();
      return;
    }
    finally
    {
      localParcel2.recycle();
      localParcel1.recycle();
    }
  }
  
  public IBinder asBinder()
  {
    return this.a;
  }
  
  public float b()
  {
    Parcel localParcel1 = Parcel.obtain();
    Parcel localParcel2 = Parcel.obtain();
    try
    {
      localParcel1.writeInterfaceToken("com.google.android.gms.maps.internal.IGoogleMapDelegate");
      this.a.transact(2, localParcel1, localParcel2, 0);
      localParcel2.readException();
      float f = localParcel2.readFloat();
      return f;
    }
    finally
    {
      localParcel2.recycle();
      localParcel1.recycle();
    }
  }
  
  /* Error */
  public void b(android.os.Bundle paramBundle)
  {
    // Byte code:
    //   0: invokestatic 22	android/os/Parcel:obtain	()Landroid/os/Parcel;
    //   3: astore_2
    //   4: invokestatic 22	android/os/Parcel:obtain	()Landroid/os/Parcel;
    //   7: astore_3
    //   8: aload_2
    //   9: ldc 24
    //   11: invokevirtual 28	android/os/Parcel:writeInterfaceToken	(Ljava/lang/String;)V
    //   14: aload_1
    //   15: ifnull +54 -> 69
    //   18: aload_2
    //   19: iconst_1
    //   20: invokevirtual 60	android/os/Parcel:writeInt	(I)V
    //   23: aload_1
    //   24: aload_2
    //   25: iconst_0
    //   26: invokevirtual 133	android/os/Bundle:writeToParcel	(Landroid/os/Parcel;I)V
    //   29: aload_0
    //   30: getfield 15	com/google/android/gms/maps/internal/IGoogleMapDelegate$a$a:a	Landroid/os/IBinder;
    //   33: bipush 60
    //   35: aload_2
    //   36: aload_3
    //   37: iconst_0
    //   38: invokeinterface 34 5 0
    //   43: pop
    //   44: aload_3
    //   45: invokevirtual 37	android/os/Parcel:readException	()V
    //   48: aload_3
    //   49: invokevirtual 41	android/os/Parcel:readInt	()I
    //   52: ifeq +8 -> 60
    //   55: aload_1
    //   56: aload_3
    //   57: invokevirtual 226	android/os/Bundle:readFromParcel	(Landroid/os/Parcel;)V
    //   60: aload_3
    //   61: invokevirtual 55	android/os/Parcel:recycle	()V
    //   64: aload_2
    //   65: invokevirtual 55	android/os/Parcel:recycle	()V
    //   68: return
    //   69: aload_2
    //   70: iconst_0
    //   71: invokevirtual 60	android/os/Parcel:writeInt	(I)V
    //   74: goto -45 -> 29
    //   77: astore 4
    //   79: aload_3
    //   80: invokevirtual 55	android/os/Parcel:recycle	()V
    //   83: aload_2
    //   84: invokevirtual 55	android/os/Parcel:recycle	()V
    //   87: aload 4
    //   89: athrow
    // Local variable table:
    //   start	length	slot	name	signature
    //   0	90	0	this	a
    //   0	90	1	paramBundle	android.os.Bundle
    //   3	81	2	localParcel1	Parcel
    //   7	73	3	localParcel2	Parcel
    //   77	11	4	localObject	Object
    // Exception table:
    //   from	to	target	type
    //   8	14	77	finally
    //   18	29	77	finally
    //   29	60	77	finally
    //   69	74	77	finally
  }
  
  /* Error */
  public void b(com.google.android.gms.dynamic.d paramd)
  {
    // Byte code:
    //   0: invokestatic 22	android/os/Parcel:obtain	()Landroid/os/Parcel;
    //   3: astore_2
    //   4: invokestatic 22	android/os/Parcel:obtain	()Landroid/os/Parcel;
    //   7: astore_3
    //   8: aload_2
    //   9: ldc 24
    //   11: invokevirtual 28	android/os/Parcel:writeInterfaceToken	(Ljava/lang/String;)V
    //   14: aload_1
    //   15: ifnull +44 -> 59
    //   18: aload_1
    //   19: invokeinterface 139 1 0
    //   24: astore 5
    //   26: aload_2
    //   27: aload 5
    //   29: invokevirtual 142	android/os/Parcel:writeStrongBinder	(Landroid/os/IBinder;)V
    //   32: aload_0
    //   33: getfield 15	com/google/android/gms/maps/internal/IGoogleMapDelegate$a$a:a	Landroid/os/IBinder;
    //   36: iconst_5
    //   37: aload_2
    //   38: aload_3
    //   39: iconst_0
    //   40: invokeinterface 34 5 0
    //   45: pop
    //   46: aload_3
    //   47: invokevirtual 37	android/os/Parcel:readException	()V
    //   50: aload_3
    //   51: invokevirtual 55	android/os/Parcel:recycle	()V
    //   54: aload_2
    //   55: invokevirtual 55	android/os/Parcel:recycle	()V
    //   58: return
    //   59: aconst_null
    //   60: astore 5
    //   62: goto -36 -> 26
    //   65: astore 4
    //   67: aload_3
    //   68: invokevirtual 55	android/os/Parcel:recycle	()V
    //   71: aload_2
    //   72: invokevirtual 55	android/os/Parcel:recycle	()V
    //   75: aload 4
    //   77: athrow
    // Local variable table:
    //   start	length	slot	name	signature
    //   0	78	0	this	a
    //   0	78	1	paramd	com.google.android.gms.dynamic.d
    //   3	69	2	localParcel1	Parcel
    //   7	61	3	localParcel2	Parcel
    //   65	11	4	localObject	Object
    //   24	37	5	localIBinder	IBinder
    // Exception table:
    //   from	to	target	type
    //   8	14	65	finally
    //   18	26	65	finally
    //   26	50	65	finally
  }
  
  /* Error */
  public void b(c paramc)
  {
    // Byte code:
    //   0: invokestatic 22	android/os/Parcel:obtain	()Landroid/os/Parcel;
    //   3: astore_2
    //   4: invokestatic 22	android/os/Parcel:obtain	()Landroid/os/Parcel;
    //   7: astore_3
    //   8: aload_2
    //   9: ldc 24
    //   11: invokevirtual 28	android/os/Parcel:writeInterfaceToken	(Ljava/lang/String;)V
    //   14: aload_1
    //   15: ifnull +42 -> 57
    //   18: aload_2
    //   19: iconst_1
    //   20: invokevirtual 60	android/os/Parcel:writeInt	(I)V
    //   23: aload_1
    //   24: aload_2
    //   25: iconst_0
    //   26: invokevirtual 211	com/google/android/gms/maps/model/internal/c:writeToParcel	(Landroid/os/Parcel;I)V
    //   29: aload_0
    //   30: getfield 15	com/google/android/gms/maps/internal/IGoogleMapDelegate$a$a:a	Landroid/os/IBinder;
    //   33: bipush 65
    //   35: aload_2
    //   36: aload_3
    //   37: iconst_0
    //   38: invokeinterface 34 5 0
    //   43: pop
    //   44: aload_3
    //   45: invokevirtual 37	android/os/Parcel:readException	()V
    //   48: aload_3
    //   49: invokevirtual 55	android/os/Parcel:recycle	()V
    //   52: aload_2
    //   53: invokevirtual 55	android/os/Parcel:recycle	()V
    //   56: return
    //   57: aload_2
    //   58: iconst_0
    //   59: invokevirtual 60	android/os/Parcel:writeInt	(I)V
    //   62: goto -33 -> 29
    //   65: astore 4
    //   67: aload_3
    //   68: invokevirtual 55	android/os/Parcel:recycle	()V
    //   71: aload_2
    //   72: invokevirtual 55	android/os/Parcel:recycle	()V
    //   75: aload 4
    //   77: athrow
    // Local variable table:
    //   start	length	slot	name	signature
    //   0	78	0	this	a
    //   0	78	1	paramc	c
    //   3	69	2	localParcel1	Parcel
    //   7	61	3	localParcel2	Parcel
    //   65	11	4	localObject	Object
    // Exception table:
    //   from	to	target	type
    //   8	14	65	finally
    //   18	29	65	finally
    //   29	48	65	finally
    //   57	62	65	finally
  }
  
  /* Error */
  public boolean b(boolean paramBoolean)
  {
    // Byte code:
    //   0: iconst_1
    //   1: istore_2
    //   2: invokestatic 22	android/os/Parcel:obtain	()Landroid/os/Parcel;
    //   5: astore_3
    //   6: invokestatic 22	android/os/Parcel:obtain	()Landroid/os/Parcel;
    //   9: astore 4
    //   11: aload_3
    //   12: ldc 24
    //   14: invokevirtual 28	android/os/Parcel:writeInterfaceToken	(Ljava/lang/String;)V
    //   17: iload_1
    //   18: ifeq +56 -> 74
    //   21: iload_2
    //   22: istore 6
    //   24: aload_3
    //   25: iload 6
    //   27: invokevirtual 60	android/os/Parcel:writeInt	(I)V
    //   30: aload_0
    //   31: getfield 15	com/google/android/gms/maps/internal/IGoogleMapDelegate$a$a:a	Landroid/os/IBinder;
    //   34: bipush 20
    //   36: aload_3
    //   37: aload 4
    //   39: iconst_0
    //   40: invokeinterface 34 5 0
    //   45: pop
    //   46: aload 4
    //   48: invokevirtual 37	android/os/Parcel:readException	()V
    //   51: aload 4
    //   53: invokevirtual 41	android/os/Parcel:readInt	()I
    //   56: istore 8
    //   58: iload 8
    //   60: ifeq +20 -> 80
    //   63: aload 4
    //   65: invokevirtual 55	android/os/Parcel:recycle	()V
    //   68: aload_3
    //   69: invokevirtual 55	android/os/Parcel:recycle	()V
    //   72: iload_2
    //   73: ireturn
    //   74: iconst_0
    //   75: istore 6
    //   77: goto -53 -> 24
    //   80: iconst_0
    //   81: istore_2
    //   82: goto -19 -> 63
    //   85: astore 5
    //   87: aload 4
    //   89: invokevirtual 55	android/os/Parcel:recycle	()V
    //   92: aload_3
    //   93: invokevirtual 55	android/os/Parcel:recycle	()V
    //   96: aload 5
    //   98: athrow
    // Local variable table:
    //   start	length	slot	name	signature
    //   0	99	0	this	a
    //   0	99	1	paramBoolean	boolean
    //   1	81	2	i	int
    //   5	88	3	localParcel1	Parcel
    //   9	79	4	localParcel2	Parcel
    //   85	12	5	localObject	Object
    //   22	4	6	j	int
    //   75	1	6	k	int
    //   56	3	8	m	int
    // Exception table:
    //   from	to	target	type
    //   11	17	85	finally
    //   24	58	85	finally
  }
  
  public float c()
  {
    Parcel localParcel1 = Parcel.obtain();
    Parcel localParcel2 = Parcel.obtain();
    try
    {
      localParcel1.writeInterfaceToken("com.google.android.gms.maps.internal.IGoogleMapDelegate");
      this.a.transact(3, localParcel1, localParcel2, 0);
      localParcel2.readException();
      float f = localParcel2.readFloat();
      return f;
    }
    finally
    {
      localParcel2.recycle();
      localParcel1.recycle();
    }
  }
  
  public void c(boolean paramBoolean)
  {
    Parcel localParcel1 = Parcel.obtain();
    Parcel localParcel2 = Parcel.obtain();
    try
    {
      localParcel1.writeInterfaceToken("com.google.android.gms.maps.internal.IGoogleMapDelegate");
      int i = 0;
      if (paramBoolean) {
        i = 1;
      }
      localParcel1.writeInt(i);
      this.a.transact(22, localParcel1, localParcel2, 0);
      localParcel2.readException();
      return;
    }
    finally
    {
      localParcel2.recycle();
      localParcel1.recycle();
    }
  }
  
  public void d()
  {
    Parcel localParcel1 = Parcel.obtain();
    Parcel localParcel2 = Parcel.obtain();
    try
    {
      localParcel1.writeInterfaceToken("com.google.android.gms.maps.internal.IGoogleMapDelegate");
      this.a.transact(8, localParcel1, localParcel2, 0);
      localParcel2.readException();
      return;
    }
    finally
    {
      localParcel2.recycle();
      localParcel1.recycle();
    }
  }
  
  public void d(boolean paramBoolean)
  {
    Parcel localParcel1 = Parcel.obtain();
    Parcel localParcel2 = Parcel.obtain();
    try
    {
      localParcel1.writeInterfaceToken("com.google.android.gms.maps.internal.IGoogleMapDelegate");
      int i = 0;
      if (paramBoolean) {
        i = 1;
      }
      localParcel1.writeInt(i);
      this.a.transact(41, localParcel1, localParcel2, 0);
      localParcel2.readException();
      return;
    }
    finally
    {
      localParcel2.recycle();
      localParcel1.recycle();
    }
  }
  
  public void e()
  {
    Parcel localParcel1 = Parcel.obtain();
    Parcel localParcel2 = Parcel.obtain();
    try
    {
      localParcel1.writeInterfaceToken("com.google.android.gms.maps.internal.IGoogleMapDelegate");
      this.a.transact(14, localParcel1, localParcel2, 0);
      localParcel2.readException();
      return;
    }
    finally
    {
      localParcel2.recycle();
      localParcel1.recycle();
    }
  }
  
  public int f()
  {
    Parcel localParcel1 = Parcel.obtain();
    Parcel localParcel2 = Parcel.obtain();
    try
    {
      localParcel1.writeInterfaceToken("com.google.android.gms.maps.internal.IGoogleMapDelegate");
      this.a.transact(15, localParcel1, localParcel2, 0);
      localParcel2.readException();
      int i = localParcel2.readInt();
      return i;
    }
    finally
    {
      localParcel2.recycle();
      localParcel1.recycle();
    }
  }
  
  public boolean g()
  {
    Parcel localParcel1 = Parcel.obtain();
    Parcel localParcel2 = Parcel.obtain();
    try
    {
      localParcel1.writeInterfaceToken("com.google.android.gms.maps.internal.IGoogleMapDelegate");
      this.a.transact(17, localParcel1, localParcel2, 0);
      localParcel2.readException();
      int i = localParcel2.readInt();
      boolean bool = false;
      if (i != 0) {
        bool = true;
      }
      return bool;
    }
    finally
    {
      localParcel2.recycle();
      localParcel1.recycle();
    }
  }
  
  public boolean h()
  {
    Parcel localParcel1 = Parcel.obtain();
    Parcel localParcel2 = Parcel.obtain();
    try
    {
      localParcel1.writeInterfaceToken("com.google.android.gms.maps.internal.IGoogleMapDelegate");
      this.a.transact(19, localParcel1, localParcel2, 0);
      localParcel2.readException();
      int i = localParcel2.readInt();
      boolean bool = false;
      if (i != 0) {
        bool = true;
      }
      return bool;
    }
    finally
    {
      localParcel2.recycle();
      localParcel1.recycle();
    }
  }
  
  public boolean i()
  {
    Parcel localParcel1 = Parcel.obtain();
    Parcel localParcel2 = Parcel.obtain();
    try
    {
      localParcel1.writeInterfaceToken("com.google.android.gms.maps.internal.IGoogleMapDelegate");
      this.a.transact(21, localParcel1, localParcel2, 0);
      localParcel2.readException();
      int i = localParcel2.readInt();
      boolean bool = false;
      if (i != 0) {
        bool = true;
      }
      return bool;
    }
    finally
    {
      localParcel2.recycle();
      localParcel1.recycle();
    }
  }
  
  /* Error */
  public android.location.Location j()
  {
    // Byte code:
    //   0: invokestatic 22	android/os/Parcel:obtain	()Landroid/os/Parcel;
    //   3: astore_1
    //   4: invokestatic 22	android/os/Parcel:obtain	()Landroid/os/Parcel;
    //   7: astore_2
    //   8: aload_1
    //   9: ldc 24
    //   11: invokevirtual 28	android/os/Parcel:writeInterfaceToken	(Ljava/lang/String;)V
    //   14: aload_0
    //   15: getfield 15	com/google/android/gms/maps/internal/IGoogleMapDelegate$a$a:a	Landroid/os/IBinder;
    //   18: bipush 23
    //   20: aload_1
    //   21: aload_2
    //   22: iconst_0
    //   23: invokeinterface 34 5 0
    //   28: pop
    //   29: aload_2
    //   30: invokevirtual 37	android/os/Parcel:readException	()V
    //   33: aload_2
    //   34: invokevirtual 41	android/os/Parcel:readInt	()I
    //   37: ifeq +28 -> 65
    //   40: getstatic 242	android/location/Location:CREATOR	Landroid/os/Parcelable$Creator;
    //   43: aload_2
    //   44: invokeinterface 248 2 0
    //   49: checkcast 239	android/location/Location
    //   52: astore 5
    //   54: aload_2
    //   55: invokevirtual 55	android/os/Parcel:recycle	()V
    //   58: aload_1
    //   59: invokevirtual 55	android/os/Parcel:recycle	()V
    //   62: aload 5
    //   64: areturn
    //   65: aconst_null
    //   66: astore 5
    //   68: goto -14 -> 54
    //   71: astore_3
    //   72: aload_2
    //   73: invokevirtual 55	android/os/Parcel:recycle	()V
    //   76: aload_1
    //   77: invokevirtual 55	android/os/Parcel:recycle	()V
    //   80: aload_3
    //   81: athrow
    // Local variable table:
    //   start	length	slot	name	signature
    //   0	82	0	this	a
    //   3	74	1	localParcel1	Parcel
    //   7	66	2	localParcel2	Parcel
    //   71	10	3	localObject	Object
    //   52	15	5	localLocation	android.location.Location
    // Exception table:
    //   from	to	target	type
    //   8	54	71	finally
  }
  
  public IUiSettingsDelegate k()
  {
    Parcel localParcel1 = Parcel.obtain();
    Parcel localParcel2 = Parcel.obtain();
    try
    {
      localParcel1.writeInterfaceToken("com.google.android.gms.maps.internal.IGoogleMapDelegate");
      this.a.transact(25, localParcel1, localParcel2, 0);
      localParcel2.readException();
      IUiSettingsDelegate localIUiSettingsDelegate = IUiSettingsDelegate.a.a(localParcel2.readStrongBinder());
      return localIUiSettingsDelegate;
    }
    finally
    {
      localParcel2.recycle();
      localParcel1.recycle();
    }
  }
  
  public IProjectionDelegate l()
  {
    Parcel localParcel1 = Parcel.obtain();
    Parcel localParcel2 = Parcel.obtain();
    try
    {
      localParcel1.writeInterfaceToken("com.google.android.gms.maps.internal.IGoogleMapDelegate");
      this.a.transact(26, localParcel1, localParcel2, 0);
      localParcel2.readException();
      IProjectionDelegate localIProjectionDelegate = IProjectionDelegate.a.a(localParcel2.readStrongBinder());
      return localIProjectionDelegate;
    }
    finally
    {
      localParcel2.recycle();
      localParcel1.recycle();
    }
  }
  
  public boolean m()
  {
    Parcel localParcel1 = Parcel.obtain();
    Parcel localParcel2 = Parcel.obtain();
    try
    {
      localParcel1.writeInterfaceToken("com.google.android.gms.maps.internal.IGoogleMapDelegate");
      this.a.transact(40, localParcel1, localParcel2, 0);
      localParcel2.readException();
      int i = localParcel2.readInt();
      boolean bool = false;
      if (i != 0) {
        bool = true;
      }
      return bool;
    }
    finally
    {
      localParcel2.recycle();
      localParcel1.recycle();
    }
  }
  
  public j n()
  {
    Parcel localParcel1 = Parcel.obtain();
    Parcel localParcel2 = Parcel.obtain();
    try
    {
      localParcel1.writeInterfaceToken("com.google.android.gms.maps.internal.IGoogleMapDelegate");
      this.a.transact(44, localParcel1, localParcel2, 0);
      localParcel2.readException();
      j localj = j.a.a(localParcel2.readStrongBinder());
      return localj;
    }
    finally
    {
      localParcel2.recycle();
      localParcel1.recycle();
    }
  }
  
  public void o()
  {
    Parcel localParcel1 = Parcel.obtain();
    Parcel localParcel2 = Parcel.obtain();
    try
    {
      localParcel1.writeInterfaceToken("com.google.android.gms.maps.internal.IGoogleMapDelegate");
      this.a.transact(55, localParcel1, localParcel2, 0);
      localParcel2.readException();
      return;
    }
    finally
    {
      localParcel2.recycle();
      localParcel1.recycle();
    }
  }
  
  public void p()
  {
    Parcel localParcel1 = Parcel.obtain();
    Parcel localParcel2 = Parcel.obtain();
    try
    {
      localParcel1.writeInterfaceToken("com.google.android.gms.maps.internal.IGoogleMapDelegate");
      this.a.transact(56, localParcel1, localParcel2, 0);
      localParcel2.readException();
      return;
    }
    finally
    {
      localParcel2.recycle();
      localParcel1.recycle();
    }
  }
  
  public void q()
  {
    Parcel localParcel1 = Parcel.obtain();
    Parcel localParcel2 = Parcel.obtain();
    try
    {
      localParcel1.writeInterfaceToken("com.google.android.gms.maps.internal.IGoogleMapDelegate");
      this.a.transact(57, localParcel1, localParcel2, 0);
      localParcel2.readException();
      return;
    }
    finally
    {
      localParcel2.recycle();
      localParcel1.recycle();
    }
  }
  
  public void r()
  {
    Parcel localParcel1 = Parcel.obtain();
    Parcel localParcel2 = Parcel.obtain();
    try
    {
      localParcel1.writeInterfaceToken("com.google.android.gms.maps.internal.IGoogleMapDelegate");
      this.a.transact(58, localParcel1, localParcel2, 0);
      localParcel2.readException();
      return;
    }
    finally
    {
      localParcel2.recycle();
      localParcel1.recycle();
    }
  }
  
  public boolean s()
  {
    Parcel localParcel1 = Parcel.obtain();
    Parcel localParcel2 = Parcel.obtain();
    try
    {
      localParcel1.writeInterfaceToken("com.google.android.gms.maps.internal.IGoogleMapDelegate");
      this.a.transact(59, localParcel1, localParcel2, 0);
      localParcel2.readException();
      int i = localParcel2.readInt();
      boolean bool = false;
      if (i != 0) {
        bool = true;
      }
      return bool;
    }
    finally
    {
      localParcel2.recycle();
      localParcel1.recycle();
    }
  }
}


/* Location:           C:\DISKD\fishfinder\apktool-install-windows-r05-ibot\classes_dex2jar.jar
 * Qualified Name:     com.google.android.gms.maps.internal.IGoogleMapDelegate.a.a
 * JD-Core Version:    0.7.0.1
 */