package com.telesoftas.deeper.activities;

import com.fridaylab.util.AsyncDelegate;

class MainDeeperActivity$SendEmailTask
  extends AsyncDelegate
{
  private MainDeeperActivity$SendEmailTask(MainDeeperActivity paramMainDeeperActivity) {}
  
  /* Error */
  protected void d()
  {
    // Byte code:
    //   0: iconst_3
    //   1: istore_1
    //   2: iconst_0
    //   3: istore_2
    //   4: aload_0
    //   5: getfield 10	com/telesoftas/deeper/activities/MainDeeperActivity$SendEmailTask:a	Lcom/telesoftas/deeper/activities/MainDeeperActivity;
    //   8: invokestatic 29	com/telesoftas/deeper/activities/MainDeeperActivity:k	(Lcom/telesoftas/deeper/activities/MainDeeperActivity;)Landroid/content/SharedPreferences;
    //   11: ldc 31
    //   13: iconst_0
    //   14: invokeinterface 37 3 0
    //   19: istore_3
    //   20: iload_3
    //   21: iload_1
    //   22: if_icmpne +4 -> 26
    //   25: return
    //   26: aload_0
    //   27: getfield 10	com/telesoftas/deeper/activities/MainDeeperActivity$SendEmailTask:a	Lcom/telesoftas/deeper/activities/MainDeeperActivity;
    //   30: invokestatic 29	com/telesoftas/deeper/activities/MainDeeperActivity:k	(Lcom/telesoftas/deeper/activities/MainDeeperActivity;)Landroid/content/SharedPreferences;
    //   33: ldc 39
    //   35: ldc 40
    //   37: invokeinterface 44 3 0
    //   42: invokestatic 50	java/lang/Float:toString	(F)Ljava/lang/String;
    //   45: astore 4
    //   47: aload_0
    //   48: getfield 10	com/telesoftas/deeper/activities/MainDeeperActivity$SendEmailTask:a	Lcom/telesoftas/deeper/activities/MainDeeperActivity;
    //   51: invokestatic 29	com/telesoftas/deeper/activities/MainDeeperActivity:k	(Lcom/telesoftas/deeper/activities/MainDeeperActivity;)Landroid/content/SharedPreferences;
    //   54: ldc 52
    //   56: ldc 40
    //   58: invokeinterface 44 3 0
    //   63: invokestatic 50	java/lang/Float:toString	(F)Ljava/lang/String;
    //   66: astore 5
    //   68: aload_0
    //   69: getfield 10	com/telesoftas/deeper/activities/MainDeeperActivity$SendEmailTask:a	Lcom/telesoftas/deeper/activities/MainDeeperActivity;
    //   72: invokestatic 29	com/telesoftas/deeper/activities/MainDeeperActivity:k	(Lcom/telesoftas/deeper/activities/MainDeeperActivity;)Landroid/content/SharedPreferences;
    //   75: ldc 54
    //   77: ldc 56
    //   79: invokeinterface 60 3 0
    //   84: astore 6
    //   86: aload_0
    //   87: getfield 10	com/telesoftas/deeper/activities/MainDeeperActivity$SendEmailTask:a	Lcom/telesoftas/deeper/activities/MainDeeperActivity;
    //   90: invokestatic 29	com/telesoftas/deeper/activities/MainDeeperActivity:k	(Lcom/telesoftas/deeper/activities/MainDeeperActivity;)Landroid/content/SharedPreferences;
    //   93: ldc 62
    //   95: ldc 64
    //   97: invokeinterface 60 3 0
    //   102: astore 7
    //   104: ldc 66
    //   106: invokestatic 72	android/net/Uri:parse	(Ljava/lang/String;)Landroid/net/Uri;
    //   109: invokevirtual 76	android/net/Uri:buildUpon	()Landroid/net/Uri$Builder;
    //   112: ldc 78
    //   114: aload 4
    //   116: invokevirtual 84	android/net/Uri$Builder:appendQueryParameter	(Ljava/lang/String;Ljava/lang/String;)Landroid/net/Uri$Builder;
    //   119: ldc 86
    //   121: aload 5
    //   123: invokevirtual 84	android/net/Uri$Builder:appendQueryParameter	(Ljava/lang/String;Ljava/lang/String;)Landroid/net/Uri$Builder;
    //   126: ldc 88
    //   128: aload 6
    //   130: invokevirtual 84	android/net/Uri$Builder:appendQueryParameter	(Ljava/lang/String;Ljava/lang/String;)Landroid/net/Uri$Builder;
    //   133: ldc 90
    //   135: aload 7
    //   137: invokevirtual 84	android/net/Uri$Builder:appendQueryParameter	(Ljava/lang/String;Ljava/lang/String;)Landroid/net/Uri$Builder;
    //   140: ldc 92
    //   142: ldc 94
    //   144: invokevirtual 84	android/net/Uri$Builder:appendQueryParameter	(Ljava/lang/String;Ljava/lang/String;)Landroid/net/Uri$Builder;
    //   147: invokevirtual 98	android/net/Uri$Builder:build	()Landroid/net/Uri;
    //   150: invokevirtual 101	android/net/Uri:toString	()Ljava/lang/String;
    //   153: astore 8
    //   155: new 103	java/net/URL
    //   158: dup
    //   159: aload 8
    //   161: invokespecial 106	java/net/URL:<init>	(Ljava/lang/String;)V
    //   164: astore 9
    //   166: invokestatic 112	java/lang/System:nanoTime	()J
    //   169: lstore 26
    //   171: aload 9
    //   173: invokevirtual 116	java/net/URL:openConnection	()Ljava/net/URLConnection;
    //   176: checkcast 118	java/net/HttpURLConnection
    //   179: astore 12
    //   181: new 120	java/io/BufferedInputStream
    //   184: dup
    //   185: aload 12
    //   187: invokevirtual 124	java/net/HttpURLConnection:getInputStream	()Ljava/io/InputStream;
    //   190: invokespecial 127	java/io/BufferedInputStream:<init>	(Ljava/io/InputStream;)V
    //   193: invokestatic 132	com/telesoftas/utilities/weather/WeatherService:a	(Ljava/io/InputStream;)Ljava/lang/String;
    //   196: astore 31
    //   198: aload_0
    //   199: getfield 10	com/telesoftas/deeper/activities/MainDeeperActivity$SendEmailTask:a	Lcom/telesoftas/deeper/activities/MainDeeperActivity;
    //   202: invokevirtual 136	com/telesoftas/deeper/activities/MainDeeperActivity:m	()Lcom/google/analytics/tracking/android/EasyTracker;
    //   205: ldc 138
    //   207: invokestatic 112	java/lang/System:nanoTime	()J
    //   210: lload 26
    //   212: lsub
    //   213: invokestatic 143	com/fridaylab/util/TimeSpan:a	(J)J
    //   216: invokestatic 149	java/lang/Long:valueOf	(J)Ljava/lang/Long;
    //   219: ldc 151
    //   221: aconst_null
    //   222: invokestatic 156	com/google/analytics/tracking/android/MapBuilder:a	(Ljava/lang/String;Ljava/lang/Long;Ljava/lang/String;Ljava/lang/String;)Lcom/google/analytics/tracking/android/MapBuilder;
    //   225: invokevirtual 159	com/google/analytics/tracking/android/MapBuilder:a	()Ljava/util/Map;
    //   228: invokevirtual 164	com/google/analytics/tracking/android/EasyTracker:a	(Ljava/util/Map;)V
    //   231: new 166	org/json/JSONObject
    //   234: dup
    //   235: aload 31
    //   237: invokespecial 167	org/json/JSONObject:<init>	(Ljava/lang/String;)V
    //   240: ldc 169
    //   242: invokevirtual 172	org/json/JSONObject:getString	(Ljava/lang/String;)Ljava/lang/String;
    //   245: ldc 174
    //   247: invokevirtual 180	java/lang/String:equals	(Ljava/lang/Object;)Z
    //   250: istore_2
    //   251: aload_0
    //   252: getfield 10	com/telesoftas/deeper/activities/MainDeeperActivity$SendEmailTask:a	Lcom/telesoftas/deeper/activities/MainDeeperActivity;
    //   255: invokestatic 29	com/telesoftas/deeper/activities/MainDeeperActivity:k	(Lcom/telesoftas/deeper/activities/MainDeeperActivity;)Landroid/content/SharedPreferences;
    //   258: invokeinterface 184 1 0
    //   263: astore 32
    //   265: iload_2
    //   266: ifeq +64 -> 330
    //   269: aload 32
    //   271: ldc 31
    //   273: iload_1
    //   274: invokeinterface 190 3 0
    //   279: invokeinterface 193 1 0
    //   284: aload 12
    //   286: ifnull +8 -> 294
    //   289: aload 12
    //   291: invokevirtual 196	java/net/HttpURLConnection:disconnect	()V
    //   294: aload_0
    //   295: getfield 10	com/telesoftas/deeper/activities/MainDeeperActivity$SendEmailTask:a	Lcom/telesoftas/deeper/activities/MainDeeperActivity;
    //   298: invokevirtual 136	com/telesoftas/deeper/activities/MainDeeperActivity:m	()Lcom/google/analytics/tracking/android/EasyTracker;
    //   301: astore 33
    //   303: iload_2
    //   304: ifeq +31 -> 335
    //   307: ldc 198
    //   309: astore 34
    //   311: aload 33
    //   313: ldc 200
    //   315: ldc 202
    //   317: aload 34
    //   319: aconst_null
    //   320: invokestatic 205	com/google/analytics/tracking/android/MapBuilder:a	(Ljava/lang/String;Ljava/lang/String;Ljava/lang/String;Ljava/lang/Long;)Lcom/google/analytics/tracking/android/MapBuilder;
    //   323: invokevirtual 159	com/google/analytics/tracking/android/MapBuilder:a	()Ljava/util/Map;
    //   326: invokevirtual 164	com/google/analytics/tracking/android/EasyTracker:a	(Ljava/util/Map;)V
    //   329: return
    //   330: iconst_2
    //   331: istore_1
    //   332: goto -63 -> 269
    //   335: ldc 207
    //   337: astore 34
    //   339: goto -28 -> 311
    //   342: astore 23
    //   344: aconst_null
    //   345: astore 19
    //   347: aload 23
    //   349: invokestatic 212	com/crashlytics/android/Crashlytics:a	(Ljava/lang/Throwable;)V
    //   352: aload 19
    //   354: ifnull +8 -> 362
    //   357: aload 19
    //   359: invokevirtual 196	java/net/HttpURLConnection:disconnect	()V
    //   362: aload_0
    //   363: getfield 10	com/telesoftas/deeper/activities/MainDeeperActivity$SendEmailTask:a	Lcom/telesoftas/deeper/activities/MainDeeperActivity;
    //   366: invokevirtual 136	com/telesoftas/deeper/activities/MainDeeperActivity:m	()Lcom/google/analytics/tracking/android/EasyTracker;
    //   369: astore 24
    //   371: iload_2
    //   372: ifeq +26 -> 398
    //   375: ldc 198
    //   377: astore 25
    //   379: aload 24
    //   381: ldc 200
    //   383: ldc 202
    //   385: aload 25
    //   387: aconst_null
    //   388: invokestatic 205	com/google/analytics/tracking/android/MapBuilder:a	(Ljava/lang/String;Ljava/lang/String;Ljava/lang/String;Ljava/lang/Long;)Lcom/google/analytics/tracking/android/MapBuilder;
    //   391: invokevirtual 159	com/google/analytics/tracking/android/MapBuilder:a	()Ljava/util/Map;
    //   394: invokevirtual 164	com/google/analytics/tracking/android/EasyTracker:a	(Ljava/util/Map;)V
    //   397: return
    //   398: ldc 207
    //   400: astore 25
    //   402: goto -23 -> 379
    //   405: astore 18
    //   407: aconst_null
    //   408: astore 19
    //   410: aload 18
    //   412: invokestatic 212	com/crashlytics/android/Crashlytics:a	(Ljava/lang/Throwable;)V
    //   415: aload 19
    //   417: ifnull +8 -> 425
    //   420: aload 19
    //   422: invokevirtual 196	java/net/HttpURLConnection:disconnect	()V
    //   425: aload_0
    //   426: getfield 10	com/telesoftas/deeper/activities/MainDeeperActivity$SendEmailTask:a	Lcom/telesoftas/deeper/activities/MainDeeperActivity;
    //   429: invokevirtual 136	com/telesoftas/deeper/activities/MainDeeperActivity:m	()Lcom/google/analytics/tracking/android/EasyTracker;
    //   432: astore 21
    //   434: iload_2
    //   435: ifeq +26 -> 461
    //   438: ldc 198
    //   440: astore 22
    //   442: aload 21
    //   444: ldc 200
    //   446: ldc 202
    //   448: aload 22
    //   450: aconst_null
    //   451: invokestatic 205	com/google/analytics/tracking/android/MapBuilder:a	(Ljava/lang/String;Ljava/lang/String;Ljava/lang/String;Ljava/lang/Long;)Lcom/google/analytics/tracking/android/MapBuilder;
    //   454: invokevirtual 159	com/google/analytics/tracking/android/MapBuilder:a	()Ljava/util/Map;
    //   457: invokevirtual 164	com/google/analytics/tracking/android/EasyTracker:a	(Ljava/util/Map;)V
    //   460: return
    //   461: ldc 207
    //   463: astore 22
    //   465: goto -23 -> 442
    //   468: astore 15
    //   470: aconst_null
    //   471: astore 12
    //   473: iload_3
    //   474: iconst_2
    //   475: if_icmpne +26 -> 501
    //   478: aload_0
    //   479: getfield 10	com/telesoftas/deeper/activities/MainDeeperActivity$SendEmailTask:a	Lcom/telesoftas/deeper/activities/MainDeeperActivity;
    //   482: invokevirtual 136	com/telesoftas/deeper/activities/MainDeeperActivity:m	()Lcom/google/analytics/tracking/android/EasyTracker;
    //   485: ldc 214
    //   487: ldc 216
    //   489: aload 7
    //   491: aconst_null
    //   492: invokestatic 205	com/google/analytics/tracking/android/MapBuilder:a	(Ljava/lang/String;Ljava/lang/String;Ljava/lang/String;Ljava/lang/Long;)Lcom/google/analytics/tracking/android/MapBuilder;
    //   495: invokevirtual 159	com/google/analytics/tracking/android/MapBuilder:a	()Ljava/util/Map;
    //   498: invokevirtual 164	com/google/analytics/tracking/android/EasyTracker:a	(Ljava/util/Map;)V
    //   501: aload_0
    //   502: getfield 10	com/telesoftas/deeper/activities/MainDeeperActivity$SendEmailTask:a	Lcom/telesoftas/deeper/activities/MainDeeperActivity;
    //   505: invokestatic 29	com/telesoftas/deeper/activities/MainDeeperActivity:k	(Lcom/telesoftas/deeper/activities/MainDeeperActivity;)Landroid/content/SharedPreferences;
    //   508: invokeinterface 184 1 0
    //   513: ldc 31
    //   515: iconst_2
    //   516: invokeinterface 190 3 0
    //   521: invokeinterface 193 1 0
    //   526: aload 12
    //   528: ifnull +8 -> 536
    //   531: aload 12
    //   533: invokevirtual 196	java/net/HttpURLConnection:disconnect	()V
    //   536: aload_0
    //   537: getfield 10	com/telesoftas/deeper/activities/MainDeeperActivity$SendEmailTask:a	Lcom/telesoftas/deeper/activities/MainDeeperActivity;
    //   540: invokevirtual 136	com/telesoftas/deeper/activities/MainDeeperActivity:m	()Lcom/google/analytics/tracking/android/EasyTracker;
    //   543: astore 16
    //   545: iload_2
    //   546: ifeq +26 -> 572
    //   549: ldc 198
    //   551: astore 17
    //   553: aload 16
    //   555: ldc 200
    //   557: ldc 202
    //   559: aload 17
    //   561: aconst_null
    //   562: invokestatic 205	com/google/analytics/tracking/android/MapBuilder:a	(Ljava/lang/String;Ljava/lang/String;Ljava/lang/String;Ljava/lang/Long;)Lcom/google/analytics/tracking/android/MapBuilder;
    //   565: invokevirtual 159	com/google/analytics/tracking/android/MapBuilder:a	()Ljava/util/Map;
    //   568: invokevirtual 164	com/google/analytics/tracking/android/EasyTracker:a	(Ljava/util/Map;)V
    //   571: return
    //   572: ldc 207
    //   574: astore 17
    //   576: goto -23 -> 553
    //   579: astore 10
    //   581: aload 10
    //   583: astore 11
    //   585: aconst_null
    //   586: astore 12
    //   588: aload 12
    //   590: ifnull +8 -> 598
    //   593: aload 12
    //   595: invokevirtual 196	java/net/HttpURLConnection:disconnect	()V
    //   598: aload_0
    //   599: getfield 10	com/telesoftas/deeper/activities/MainDeeperActivity$SendEmailTask:a	Lcom/telesoftas/deeper/activities/MainDeeperActivity;
    //   602: invokevirtual 136	com/telesoftas/deeper/activities/MainDeeperActivity:m	()Lcom/google/analytics/tracking/android/EasyTracker;
    //   605: astore 13
    //   607: iload_2
    //   608: ifeq +28 -> 636
    //   611: ldc 198
    //   613: astore 14
    //   615: aload 13
    //   617: ldc 200
    //   619: ldc 202
    //   621: aload 14
    //   623: aconst_null
    //   624: invokestatic 205	com/google/analytics/tracking/android/MapBuilder:a	(Ljava/lang/String;Ljava/lang/String;Ljava/lang/String;Ljava/lang/Long;)Lcom/google/analytics/tracking/android/MapBuilder;
    //   627: invokevirtual 159	com/google/analytics/tracking/android/MapBuilder:a	()Ljava/util/Map;
    //   630: invokevirtual 164	com/google/analytics/tracking/android/EasyTracker:a	(Ljava/util/Map;)V
    //   633: aload 11
    //   635: athrow
    //   636: ldc 207
    //   638: astore 14
    //   640: goto -25 -> 615
    //   643: astore 11
    //   645: goto -57 -> 588
    //   648: astore 20
    //   650: aload 19
    //   652: astore 12
    //   654: aload 20
    //   656: astore 11
    //   658: goto -70 -> 588
    //   661: astore 30
    //   663: goto -190 -> 473
    //   666: astore 29
    //   668: aload 12
    //   670: astore 19
    //   672: aload 29
    //   674: astore 18
    //   676: goto -266 -> 410
    //   679: astore 28
    //   681: aload 12
    //   683: astore 19
    //   685: aload 28
    //   687: astore 23
    //   689: goto -342 -> 347
    // Local variable table:
    //   start	length	slot	name	signature
    //   0	692	0	this	SendEmailTask
    //   1	331	1	i	int
    //   3	605	2	bool	boolean
    //   19	457	3	j	int
    //   45	70	4	str1	java.lang.String
    //   66	56	5	str2	java.lang.String
    //   84	45	6	str3	java.lang.String
    //   102	388	7	str4	java.lang.String
    //   153	7	8	str5	java.lang.String
    //   164	8	9	localURL	java.net.URL
    //   579	3	10	localObject1	java.lang.Object
    //   583	51	11	localObject2	java.lang.Object
    //   643	1	11	localObject3	java.lang.Object
    //   656	1	11	localObject4	java.lang.Object
    //   179	503	12	localObject5	java.lang.Object
    //   605	11	13	localEasyTracker1	com.google.analytics.tracking.android.EasyTracker
    //   613	26	14	str6	java.lang.String
    //   468	1	15	localIOException1	java.io.IOException
    //   543	11	16	localEasyTracker2	com.google.analytics.tracking.android.EasyTracker
    //   551	24	17	str7	java.lang.String
    //   405	6	18	localJSONException1	org.json.JSONException
    //   674	1	18	localObject6	java.lang.Object
    //   345	339	19	localObject7	java.lang.Object
    //   648	7	20	localObject8	java.lang.Object
    //   432	11	21	localEasyTracker3	com.google.analytics.tracking.android.EasyTracker
    //   440	24	22	str8	java.lang.String
    //   342	6	23	localMalformedURLException1	java.net.MalformedURLException
    //   687	1	23	localObject9	java.lang.Object
    //   369	11	24	localEasyTracker4	com.google.analytics.tracking.android.EasyTracker
    //   377	24	25	str9	java.lang.String
    //   169	42	26	l	long
    //   679	7	28	localMalformedURLException2	java.net.MalformedURLException
    //   666	7	29	localJSONException2	org.json.JSONException
    //   661	1	30	localIOException2	java.io.IOException
    //   196	40	31	str10	java.lang.String
    //   263	7	32	localEditor	android.content.SharedPreferences.Editor
    //   301	11	33	localEasyTracker5	com.google.analytics.tracking.android.EasyTracker
    //   309	29	34	str11	java.lang.String
    // Exception table:
    //   from	to	target	type
    //   155	181	342	java/net/MalformedURLException
    //   155	181	405	org/json/JSONException
    //   155	181	468	java/io/IOException
    //   155	181	579	finally
    //   181	265	643	finally
    //   269	284	643	finally
    //   478	501	643	finally
    //   501	526	643	finally
    //   347	352	648	finally
    //   410	415	648	finally
    //   181	265	661	java/io/IOException
    //   269	284	661	java/io/IOException
    //   181	265	666	org/json/JSONException
    //   269	284	666	org/json/JSONException
    //   181	265	679	java/net/MalformedURLException
    //   269	284	679	java/net/MalformedURLException
  }
}


/* Location:           C:\DISKD\fishfinder\apktool-install-windows-r05-ibot\classes_dex2jar.jar
 * Qualified Name:     com.telesoftas.deeper.activities.MainDeeperActivity.SendEmailTask
 * JD-Core Version:    0.7.0.1
 */